Workbook

Sheet Summary
A1: LeetCode history: list "Anuj Mar-23 to present"
A2: Pulled from LeetCode on 2026-10-24 12:43 IST. Times are IST.
A4: Your list
A5: Problems in the list | B5: =COUNTA('Solved Problems'!$C$2:$C$278)
A6: Solved (LeetCode status) | B6: =COUNTIF('Solved Problems'!$I$2:$I$278,"Solved")
A7: Attempted, not solved | B7: =COUNTIF('Solved Problems'!$I$2:$I$278,"Attempted")
A8: Easy | B8: =COUNTIF('Solved Problems'!$D$2:$D$278,"Easy")
A9: Medium | B9: =COUNTIF('Solved Problems'!$D$2:$D$278,"Medium")
A10: Hard | B10: =COUNTIF('Solved Problems'!$D$2:$D$278,"Hard")
A11: Solved on the first submission | B11: =COUNTIF('Solved Problems'!$P$2:$P$278,"Yes")
A12: First-try AC rate | B12: =B11/B5
A13: Patterns covered | B13: =COUNTIF('Pattern Summary'!$F$2:$F$36,">0") | C13: out of 35 patterns in this workbook
A14: Submissions
A15: Submissions since Mar 2023 (list + other) | B15: =COUNTA(Submissions!$A$2:$A$1621)
A16: of which on your list | B16: =COUNTIF(Submissions!$N$2:$N$1621,"Yes")
A17: Accepted | B17: =COUNTIF(Submissions!$G$2:$G$1621,"Accepted")
A18: Acceptance rate | B18: =B17/B15
A19: Wrong Answer | B19: =COUNTIF(Submissions!$G$2:$G$1621,"Wrong Answer")
A20: Time Limit Exceeded | B20: =COUNTIF(Submissions!$G$2:$G$1621,"Time Limit Exceeded")
A21: Runtime Error | B21: =COUNTIF(Submissions!$G$2:$G$1621,"Runtime Error")
A22: C++ submissions | B22: =COUNTIF(Submissions!$H$2:$H$1621,"C++")
A23: Python submissions | B23: =COUNTIF(Submissions!$H$2:$H$1621,"Python3")+COUNTIF(Submissions!$H$2:$H$1621,"Python")
A24: First submission | B24: =MIN(Submissions!$A$2:$A$1621)
A25: Latest submission | B25: =MAX(Submissions!$A$2:$A$1621)
A26: Other problems (account, not in list) | B26: =COUNTA('Other Problems'!$C$2:$C$119) | C26: Solved on this account since Mar 2023 but not in your list. Mark them Y/N on that sheet.
A27: Notes
A28: Whose work counts | C28: Only submissions from 1 Mar 2023 onward are counted (the list is named "Mar-23 to present"). Older submissions on these problems are counted in the 'Pre-Mar-2023 subs (excluded)' column.
A29: Submission links | C29: Submission links open only when you are signed in to the LeetCode account that made them.
A30: Code | C30: Every attempt's code, oldest first, is in the code/ folder next to this file, one Markdown file per problem.
A31: Patterns | C31: Pattern and sub-pattern are assigned by hand from how the problem is usually solved, not taken from LeetCode tags.
A32: Runtime beats % | C32: LeetCode recomputes this against today's runtimes, so 2023-era submissions often show near 0%. Compare within a problem, not across years.

Sheet Solved Problems
A1: # | B1: LC # | C1: Problem | D1: Difficulty | E1: Pattern | F1: Sub-pattern | G1: Topic group | H1: LeetCode tags | I1: LC status | J1: First attempt | K1: First accepted | L1: Last submission | M1: Submissions | N1: Accepted | O1: Failed before first AC | P1: First-try AC? | Q1: Wrong Answer (before AC) | R1: TLE (before AC) | S1: Other errors (before AC) | T1: Languages | U1: Best runtime beats % | V1: Latest accepted submission | W1: Code & attempts file | X1: Pre-Mar-2023 subs (excluded) | Y1: First AC month
A2: 1 | B2: 1 | C2: Two Sum | D2: Easy | E2: Arrays, Hashing & Sorting | F2: Complement map | G2: Arrays & Strings | H2: array, hash-table | I2: Solved | J2: 44991.912 | K2: 44991.912 | L2: 45218.859 | M2: 7 | N2: 7 | O2: 0 | P2: =IF(AND(N2>0,O2=0),"Yes","No") | Q2: 0 | R2: 0 | S2: 0 | T2: C++ | U2: 40.6 | V2: Submission 1079247546 | W2: Open code | X2: 2 | Y2: 2023-03
A3: 2 | B3: 13 | C3: Roman to Integer | D3: Easy | E3: Strings & Simulation | F3: Parsing | G3: Arrays & Strings | H3: hash-table, math, string | I3: Solved | J3: 44991.939 | K3: 44991.939 | L3: 44992.027 | M3: 2 | N3: 2 | O3: 0 | P3: =IF(AND(N3>0,O3=0),"Yes","No") | Q3: 0 | R3: 0 | S3: 0 | T3: C++ | U3: 26.4 | V3: Submission 910366895 | W3: Open code | X3: 0 | Y3: 2023-03
A4: 3 | B4: 14 | C4: Longest Common Prefix | D4: Easy | E4: Strings & Simulation | F4: Column scan | G4: Arrays & Strings | H4: array, string, trie | I4: Solved | J4: 44991.944 | K4: 44991.945 | L4: 44992.027 | M4: 3 | N4: 2 | O4: 1 | P4: =IF(AND(N4>0,O4=0),"Yes","No") | Q4: 1 | R4: 0 | S4: 0 | T4: C++ | U4: 100 | V4: Submission 910366984 | W4: Open code | X4: 0 | Y4: 2023-03
A5: 4 | B5: 20 | C5: Valid Parentheses | D5: Easy | E5: Stack | F5: Bracket matching | G5: Stacks & Queues | H5: string, stack, bracket-sequences | I5: Solved | J5: 44991.954 | K5: 44991.958 | L5: 45318.954 | M5: 5 | N5: 3 | O5: 2 | P5: =IF(AND(N5>0,O5=0),"Yes","No") | Q5: 1 | R5: 0 | S5: 1 | T5: C++, Python3 | U5: 3.7 | V5: Submission 1158444134 | W5: Open code | X5: 3 | Y5: 2023-03
A6: 5 | B6: 359 | C6: Logger Rate Limiter | D6: Easy | E6: Design | F6: Map of last timestamps | G6: Design | H6: hash-table, design, data-stream | I6: Solved | J6: 44991.99 | K6: 44991.99 | L6: 45042.68 | M6: 5 | N6: 5 | O6: 0 | P6: =IF(AND(N6>0,O6=0),"Yes","No") | Q6: 0 | R6: 0 | S6: 0 | T6: C++ | U6: 5.2 | V6: Submission 940009478 | W6: Open code | X6: 0 | Y6: 2023-03
A7: 6 | B7: 704 | C7: Binary Search | D7: Easy | E7: Binary Search | F7: Classic search | G7: Searching | H7: array, binary-search | I7: Solved | J7: 44992.004 | K7: 44992.004 | L7: 45243.974 | M7: 7 | N7: 5 | O7: 0 | P7: =IF(AND(N7>0,O7=0),"Yes","No") | Q7: 0 | R7: 0 | S7: 0 | T7: C++, Python3 | U7: 0.2 | V7: Submission 1098074392 | W7: Open code | X7: 3 | Y7: 2023-03
A8: 7 | B8: 938 | C8: Range Sum of BST | D8: Easy | E8: Binary Search Tree | F8: Range-pruned DFS | G8: Trees | H8: tree, depth-first-search, binary-search-tree, binary-tree | I8: Solved | J8: 44992.026 | K8: 44992.026 | L8: 45854.503 | M8: 13 | N8: 13 | O8: 0 | P8: =IF(AND(N8>0,O8=0),"Yes","No") | Q8: 0 | R8: 0 | S8: 0 | T8: C++, Python3 | U8: 100 | V8: Submission 1699707053 | W8: Open code | X8: 0 | Y8: 2023-03
A9: 8 | B9: 56 | C9: Merge Intervals | D9: Medium | E9: Intervals & Sweep Line | F9: Sort and merge | G9: Heaps & Intervals | H9: array, sorting, quicksort | I9: Solved | J9: 44992.071 | K9: 44992.071 | L9: 45845.963 | M9: 16 | N9: 12 | O9: 0 | P9: =IF(AND(N9>0,O9=0),"Yes","No") | Q9: 0 | R9: 0 | S9: 0 | T9: C++, Python, Python3 | U9: 90.8 | V9: Submission 1689875947 | W9: Open code | X9: 2 | Y9: 2023-03
A10: 9 | B10: 70 | C10: Climbing Stairs | D10: Easy | E10: DP: 1D / Linear | F10: Fibonacci | G10: Dynamic Programming | H10: math, dynamic-programming, memoization | I10: Solved | J10: 44996.411 | K10: 44996.411 | L10: 44996.411 | M10: 2 | N10: 1 | O10: 1 | P10: =IF(AND(N10>0,O10=0),"Yes","No") | Q10: 1 | R10: 0 | S10: 0 | T10: C++ | U10: 100 | V10: Submission 913014080 | W10: Open code | X10: 2 | Y10: 2023-03
A11: 10 | B11: 1377 | C11: Frog Position After T Seconds | D11: Hard | E11: Graph: General BFS/DFS | F11: BFS with probability | G11: Graphs | H11: tree, depth-first-search, breadth-first-search, graph | I11: Solved | J11: 44996.601 | K11: 44996.601 | L11: 44996.642 | M11: 2 | N11: 2 | O11: 0 | P11: =IF(AND(N11>0,O11=0),"Yes","No") | Q11: 0 | R11: 0 | S11: 0 | T11: C++ | U11: 11 | V11: Submission 913148665 | W11: Open code | X11: 0 | Y11: 2023-03
A12: 11 | B12: 213 | C12: House Robber II | D12: Medium | E12: DP: 1D / Linear | F12: Take/skip, circular | G12: Dynamic Programming | H12: array, dynamic-programming | I12: Solved | J12: 44996.71 | K12: 44996.712 | L12: 44996.712 | M12: 3 | N12: 1 | O12: 2 | P12: =IF(AND(N12>0,O12=0),"Yes","No") | Q12: 2 | R12: 0 | S12: 0 | T12: C++ | U12: 6.5 | V12: Submission 913185817 | W12: Open code | X12: 0 | Y12: 2023-03
A13: 12 | B13: 64 | C13: Minimum Path Sum | D13: Medium | E13: DP: Grid / 2D | F13: Min-cost path | G13: Dynamic Programming | H13: array, dynamic-programming, matrix | I13: Solved | J13: 44997.468 | K13: 44997.47 | L13: 44997.47 | M13: 2 | N13: 1 | O13: 1 | P13: =IF(AND(N13>0,O13=0),"Yes","No") | Q13: 1 | R13: 0 | S13: 0 | T13: C++ | U13: 5.9 | V13: Submission 913635348 | W13: Open code | X13: 1 | Y13: 2023-03
... A89: 88 | B89: 1136 | C89: Parallel Courses | D89: Medium | E89: Graph: Topological Sort | F89: Kahn by levels | G89: Graphs | H89: graph, topological-sort, directed-acyclic-graph | I89: Solved | J89: 45009.838 | K89: 45009.838 | L89: 45009.848 | M89: 2 | N89: 2 | O89: 0 | P89: =IF(AND(N89>0,O89=0),"Yes","No") | Q89: 0 | R89: 0 | S89: 0 | T89: C++ | U89: 5.1 | V89: Submission 921343418 | W89: Open code | X89: 3 | Y89: 2023-03
A90: 89 | B90: 1494 | C90: Parallel Courses II | D90: Hard | E90: DP: Bitmask | F90: Bitmask DP over courses | G90: Dynamic Programming | H90: dynamic-programming, bit-manipulation, graph, bitmask, directed-acyclic-graph | I90: Attempted | J90: 45009.905 | L90: 45009.905 | M90: 1 | N90: 0 | O90: 1 | P90: =IF(AND(N90>0,O90=0),"Yes","No") | Q90: 1 | R90: 0 | S90: 0 | T90: C++ | W90: Open code | X90: 1
A91: 90 | B91: 1105 | C91: Filling Bookcase Shelves | D91: Medium | E91: DP: Partition / Interval (MCM) | F91: Front partition DP | G91: Dynamic Programming | H91: array, dynamic-programming | I91: Solved | J91: 45010.026 | K91: 45010.031 | L91: 45010.04 | M91: 4 | N91: 1 | O91: 1 | P91: =IF(AND(N91>0,O91=0),"Yes","No") | Q91: 0 | R91: 1 | S91: 0 | T91: C++ | U91: 5 | V91: Submission 921478900 | W91: Open code | X91: 0 | Y91: 2023-03
A92: 91 | B92: 366 | C92: Find Leaves of Binary Tree | D92: Medium | E92: Binary Tree (DFS & Recursion) | F92: Group by height | G92: Trees | H92: tree, depth-first-search, binary-tree, dp-on-trees | I92: Solved | J92: 45010.051 | K92: 45010.051 | L92: 45010.051 | M92: 1 | N92: 1 | O92: 0 | P92: =IF(AND(N92>0,O92=0),"Yes","No") | Q92: 0 | R92: 0 | S92: 0 | T92: C++ | U92: 0 | V92: Submission 921490889 | W92: Open code | X92: 0 | Y92: 2023-03
A93: 92 | B93: 1202 | C93: Smallest String With Swaps | D93: Medium | E93: Graph: Union-Find | F93: Components + sort | G93: Graphs | H93: array, hash-table, string, depth-first-search, breadth-first-search, union-find, sorting | I93: Solved | J93: 45010.081 | K93: 45010.081 | L93: 45010.081 | M93: 1 | N93: 1 | O93: 0 | P93: =IF(AND(N93>0,O93=0),"Yes","No") | Q93: 0 | R93: 0 | S93: 0 | T93: C++ | U93: 5 | V93: Submission 921506988 | W93: Open code | X93: 2 | Y93: 2023-03
A94: 93 | B94: 2034 | C94: Stock Price Fluctuation | D94: Medium | E94: Design | F94: Map + lazy heaps | G94: Design | H94: hash-table, design, heap-priority-queue, data-stream, ordered-set | I94: Solved | J94: 45010.098 | K94: 45010.098 | L94: 45010.098 | M94: 1 | N94: 1 | O94: 0 | P94: =IF(AND(N94>0,O94=0),"Yes","No") | Q94: 0 | R94: 0 | S94: 0 | T94: C++ | U94: 5.1 | V94: Submission 921515192 | W94: Open code | X94: 0 | Y94: 2023-03
A95: 94 | B95: 22 | C95: Generate Parentheses | D95: Medium | E95: Backtracking | F95: Balanced generation | G95: Recursion & Backtracking | H95: string, dynamic-programming, backtracking, bracket-sequences | I95: Solved | J95: 45010.139 | K95: 45010.139 | L95: 45066.613 | M95: 5 | N95: 5 | O95: 0 | P95: =IF(AND(N95>0,O95=0),"Yes","No") | Q95: 0 | R95: 0 | S95: 0 | T95: C++ | U95: 66.5 | V95: Submission 953809671 | W95: Open code | X95: 0 | Y95: 2023-03
A96: 95 | B96: 3 | C96: Longest Substring Without Repeating Characters | D96: Medium | E96: Sliding Window | F96: Variable window, unique chars | G96: Arrays & Strings | H96: hash-table, string, sliding-window | I96: Solved | J96: 45010.507 | K96: 45010.507 | L96: 45248.254 | M96: 2 | N96: 2 | O96: 0 | P96: =IF(AND(N96>0,O96=0),"Yes","No") | Q96: 0 | R96: 0 | S96: 0 | T96: C++, Python3 | U96: 99.9 | V96: Submission 1101104428 | W96: Open code | X96: 8 | Y96: 2023-03
A97: 96 | B97: 33 | C97: Search in Rotated Sorted Array | D97: Medium | E97: Binary Search | F97: Rotated array | G97: Searching | H97: array, binary-search | I97: Solved | J97: 45010.54 | K97: 45010.54 | L97: 45738.624 | M97: 8 | N97: 7 | O97: 0 | P97: =IF(AND(N97>0,O97=0),"Yes","No") | Q97: 0 | R97: 0 | S97: 0 | T97: C++, Python3 | U97: 100 | V97: Submission 1138961252 | W97: Open code | X97: 10 | Y97: 2023-03
A98: 97 | B98: 210 | C98: Course Schedule II | D98: Medium | E98: Graph: Topological Sort | F98: Kahn order | G98: Graphs | H98: depth-first-search, breadth-first-search, graph, topological-sort | I98: Solved | J98: 45010.568 | K98: 45010.568 | L98: 45010.568 | M98: 1 | N98: 1 | O98: 0 | P98: =IF(AND(N98>0,O98=0),"Yes","No") | Q98: 0 | R98: 0 | S98: 0 | T98: C++ | U98: 5.1 | V98: Submission 921728668 | W98: Open code | X98: 1 | Y98: 2023-03
A99: 98 | B99: 328 | C99: Odd Even Linked List | D99: Medium | E99: Linked List | F99: Re-linking | G99: Linked List | H99: linked-list | I99: Solved | J99: 45010.604 | K99: 45010.604 | L99: 45010.604 | M99: 1 | N99: 1 | O99: 0 | P99: =IF(AND(N99>0,O99=0),"Yes","No") | Q99: 0 | R99: 0 | S99: 0 | T99: C++ | U99: 0.7 | V99: Submission 921750222 | W99: Open code | X99: 0 | Y99: 2023-03
A100: 99 | B100: 725 | C100: Split Linked List in Parts | D100: Medium | E100: Linked List | F100: Split by length | G100: Linked List | H100: linked-list | I100: Solved | J100: 45010.625 | K100: 45010.625 | L100: 45010.625 | M100: 2 | N100: 1 | O100: 1 | P100: =IF(AND(N100>0,O100=0),"Yes","No") | Q100: 1 | R100: 0 | S100: 0 | T100: C++ | U100: 0.1 | V100: Submission 921762544 | W100: Open code | X100: 0 | Y100: 2023-03
A101: 100 | B101: 61 | C101: Rotate List | D101: Medium | E101: Linked List | F101: Rotate by k | G101: Linked List | H101: linked-list, two-pointers | I101: Solved | J101: 45010.635 | K101: 45010.638 | L101: 45010.638 | M101: 4 | N101: 1 | O101: 3 | P101: =IF(AND(N101>0,O101=0),"Yes","No") | Q101: 0 | R101: 0 | S101: 3 | T101: C++ | U101: 0.7 | V101: Submission 921770509 | W101: Open code | X101: 1 | Y101: 2023-03
A102: 101 | B102: 148 | C102: Sort List | D102: Medium | E102: Linked List | F102: Merge sort on list | G102: Linked List | H102: linked-list, two-pointers, divide-and-conquer, sorting, merge-sort | I102: Solved | J102: 45010.651 | K102: 45010.651 | L102: 45010.651 | M102: 1 | N102: 1 | O102: 0 | P102: =IF(AND(N102>0,O102=0),"Yes","No") | Q102: 0 | R102: 0 | S102: 0 | T102: C++ | U102: 5.2 | V102: Submission 921778877 | W102: Open code | X102: 1 | Y102: 2023-03
... A146: 145 | B146: 353 | C146: Design Snake Game | D146: Medium | E146: Design | F146: Deque + set | G146: Design | H146: array, hash-table, design, queue, simulation | I146: Solved | J146: 45042.582 | K146: 45042.594 | L146: 45042.676 | M146: 3 | N146: 2 | O146: 1 | P146: =IF(AND(N146>0,O146=0),"Yes","No") | Q146: 1 | R146: 0 | S146: 0 | T146: C++ | U146: 25.9 | V146: Submission 940007168 | W146: Open code | X146: 0 | Y146: 2023-04
A147: 146 | B147: 381 | C147: Insert Delete GetRandom O(1) - Duplicates allowed | D147: Hard | E147: Design | F147: Array + index map | G147: Design | H147: array, hash-table, math, design, randomized | I147: Attempted | J147: 45042.693 | L147: 45042.698 | M147: 2 | N147: 0 | O147: 2 | P147: =IF(AND(N147>0,O147=0),"Yes","No") | Q147: 1 | R147: 1 | S147: 0 | T147: C++ | W147: Open code | X147: 4
A148: 147 | B148: 39 | C148: Combination Sum | D148: Medium | E148: Backtracking | F148: Combinations with reuse | G148: Recursion & Backtracking | H148: array, backtracking | I148: Solved | J148: 45044.426 | K148: 45044.426 | L148: 45588.505 | M148: 2 | N148: 2 | O148: 0 | P148: =IF(AND(N148>0,O148=0),"Yes","No") | Q148: 0 | R148: 0 | S148: 0 | T148: C++ | U148: 100 | V148: Submission 1431182072 | W148: Open code | X148: 2 | Y148: 2023-04
A149: 148 | B149: 40 | C149: Combination Sum II | D149: Medium | E149: Backtracking | F149: Combinations with duplicates | G149: Recursion & Backtracking | H149: array, backtracking | I149: Solved | J149: 45044.439 | K149: 45044.452 | L149: 45588.512 | M149: 4 | N149: 2 | O149: 1 | P149: =IF(AND(N149>0,O149=0),"Yes","No") | Q149: 0 | R149: 1 | S149: 0 | T149: C++ | U149: 100 | V149: Submission 1431190430 | W149: Open code | X149: 0 | Y149: 2023-04
A150: 149 | B150: 51 | C150: N-Queens | D150: Hard | E150: Backtracking | F150: Constraint placement | G150: Recursion & Backtracking | H150: array, backtracking, algorithm-x | I150: Solved | J150: 45044.521 | K150: 45044.521 | L150: 45044.528 | M150: 2 | N150: 2 | O150: 0 | P150: =IF(AND(N150>0,O150=0),"Yes","No") | Q150: 0 | R150: 0 | S150: 0 | T150: C++ | U150: 13.1 | V150: Submission 940980279 | W150: Open code | X150: 3 | Y150: 2023-04
A151: 150 | B151: 37 | C151: Sudoku Solver | D151: Hard | E151: Backtracking | F151: Constraint search | G151: Recursion & Backtracking | H151: array, hash-table, backtracking, matrix, algorithm-x, dancing-links | I151: Solved | J151: 45044.554 | K151: 45044.554 | L151: 45044.554 | M151: 1 | N151: 1 | O151: 0 | P151: =IF(AND(N151>0,O151=0),"Yes","No") | Q151: 0 | R151: 0 | S151: 0 | T151: C++ | U151: 95.7 | V151: Submission 940993417 | W151: Open code | X151: 0 | Y151: 2023-04
A152: 151 | B152: 131 | C152: Palindrome Partitioning | D152: Medium | E152: Backtracking | F152: Partition backtracking | G152: Recursion & Backtracking | H152: string, dynamic-programming, backtracking | I152: Solved | J152: 45044.629 | K152: 45044.629 | L152: 45044.629 | M152: 1 | N152: 1 | O152: 0 | P152: =IF(AND(N152>0,O152=0),"Yes","No") | Q152: 0 | R152: 0 | S152: 0 | T152: C++ | U152: 12.4 | V152: Submission 941029531 | W152: Open code | X152: 0 | Y152: 2023-04
A153: 152 | B153: 60 | C153: Permutation Sequence | D153: Hard | E153: Math & Bit Manipulation | F153: Factorial number system | G153: Arrays & Strings | H153: math, recursion | I153: Solved | J153: 45044.649 | K153: 45044.663 | L153: 45044.663 | M153: 4 | N153: 1 | O153: 3 | P153: =IF(AND(N153>0,O153=0),"Yes","No") | Q153: 0 | R153: 2 | S153: 1 | T153: C++ | U153: 100 | V153: Submission 941045258 | W153: Open code | X153: 0 | Y153: 2023-04
A154: 153 | B154: 875 | C154: Koko Eating Bananas | D154: Medium | E154: Binary Search on Answer | F154: Minimise speed | G154: Searching | H154: array, binary-search | I154: Solved | J154: 45044.791 | K154: 45044.791 | L154: 45738.9 | M154: 12 | N154: 6 | O154: 0 | P154: =IF(AND(N154>0,O154=0),"Yes","No") | Q154: 0 | R154: 0 | S154: 0 | T154: C++, Python3 | U154: 52.4 | V154: Submission 1582420275 | W154: Open code | X154: 0 | Y154: 2023-04
A155: 154 | B155: 994 | C155: Rotting Oranges | D155: Medium | E155: Graph: Grid BFS/DFS | F155: Multi-source BFS | G155: Graphs | H155: array, breadth-first-search, matrix | I155: Solved | J155: 45045.38 | K155: 45045.38 | L155: 45778.43 | M155: 2 | N155: 2 | O155: 0 | P155: =IF(AND(N155>0,O155=0),"Yes","No") | Q155: 0 | R155: 0 | S155: 0 | T155: C++ | U155: 40.7 | V155: Submission 1622478711 | W155: Open code | X155: 0 | Y155: 2023-04
A156: 155 | B156: 542 | C156: 01 Matrix | D156: Medium | E156: Graph: Grid BFS/DFS | F156: Multi-source BFS | G156: Graphs | H156: array, dynamic-programming, breadth-first-search, matrix | I156: Solved | J156: 45045.406 | K156: 45045.406 | L156: 45045.407 | M156: 2 | N156: 2 | O156: 0 | P156: =IF(AND(N156>0,O156=0),"Yes","No") | Q156: 0 | R156: 0 | S156: 0 | T156: C++ | U156: 5 | V156: Submission 941376684 | W156: Open code | X156: 0 | Y156: 2023-04
A157: 156 | B157: 1020 | C157: Number of Enclaves | D157: Medium | E157: Graph: Grid BFS/DFS | F157: Border flood fill | G157: Graphs | H157: array, depth-first-search, breadth-first-search, union-find, matrix | I157: Solved | J157: 45045.441 | K157: 45045.441 | L157: 45045.441 | M157: 1 | N157: 1 | O157: 0 | P157: =IF(AND(N157>0,O157=0),"Yes","No") | Q157: 0 | R157: 0 | S157: 0 | T157: C++ | U157: 5 | V157: Submission 941390538 | W157: Open code | X157: 0 | Y157: 2023-04
A158: 157 | B158: 694 | C158: Number of Distinct Islands | D158: Medium | E158: Graph: Grid BFS/DFS | F158: Shape signature | G158: Graphs | H158: array, hash-table, depth-first-search, breadth-first-search, union-find, sorting, matrix, hash-function | I158: Solved | J158: 45045.501 | K158: 45045.501 | L158: 45217.597 | M158: 2 | N158: 2 | O158: 0 | P158: =IF(AND(N158>0,O158=0),"Yes","No") | Q158: 0 | R158: 0 | S158: 0 | T158: C++ | U158: 11.7 | V158: Submission 1078223567 | W158: Open code | X158: 1 | Y158: 2023-04
A159: 158 | B159: 785 | C159: Is Graph Bipartite? | D159: Medium | E159: Graph: General BFS/DFS | F159: Two-colouring | G159: Graphs | H159: depth-first-search, breadth-first-search, union-find, graph, graph-coloring, bipartite-graph | I159: Solved | J159: 45045.522 | K159: 45045.525 | L159: 45045.53 | M159: 3 | N159: 2 | O159: 1 | P159: =IF(AND(N159>0,O159=0),"Yes","No") | Q159: 1 | R159: 0 | S159: 0 | T159: C++ | U159: 5.2 | V159: Submission 941431927 | W159: Open code | X159: 1 | Y159: 2023-04
... A278: 277 | B278: 133 | C278: Clone Graph | D278: Medium | E278: Graph: General BFS/DFS | F278: Copy with map | G278: Graphs | H278: hash-table, depth-first-search, breadth-first-search, graph | I278: Solved | J278: 45822.948 | K278: 45822.948 | L278: 45822.951 | M278: 2 | N278: 2 | O278: 0 | P278: =IF(AND(N278>0,O278=0),"Yes","No") | Q278: 0 | R278: 0 | S278: 0 | T278: C++ | U278: 73.5 | V278: Submission 1664076025 | W278: Open code | X278: 1 | Y278: 2025-06

Sheet Other Problems
A1: # | B1: LC # | C1: Problem | D1: Difficulty | E1: Pattern | F1: Sub-pattern | G1: Topic group | H1: LeetCode tags | I1: LC status | J1: First attempt | K1: First accepted | L1: Last submission | M1: Submissions | N1: Accepted | O1: Failed before first AC | P1: First-try AC? | Q1: Wrong Answer (before AC) | R1: TLE (before AC) | S1: Other errors (before AC) | T1: Languages | U1: Best runtime beats % | V1: Latest accepted submission | W1: Code & attempts file | X1: Pre-Mar-2023 subs (excluded) | Y1: First AC month | Z1: Mine? (Y/N)
A2: 1 | B2: 1480 | C2: Running Sum of 1d Array | D2: Easy | E2: Prefix Sum & Difference Array | F2: Running sum | G2: Arrays & Strings | H2: array, prefix-sum | I2: Ac | J2: 44991.879 | K2: 44991.879 | L2: 44991.879 | M2: 1 | N2: 1 | O2: 0 | P2: =IF(AND(N2>0,O2=0),"Yes","No") | Q2: 0 | R2: 0 | S2: 0 | T2: C++ | U2: 100 | V2: Submission 910238803 | W2: Open code | X2: 0 | Y2: 2023-03
A3: 2 | B3: 724 | C3: Find Pivot Index | D3: Easy | E3: Prefix Sum & Difference Array | F3: Prefix sum | G3: Arrays & Strings | H3: array, prefix-sum | I3: Ac | J3: 44991.886 | K3: 44991.886 | L3: 45170.968 | M3: 2 | N3: 2 | O3: 0 | P3: =IF(AND(N3>0,O3=0),"Yes","No") | Q3: 0 | R3: 0 | S3: 0 | T3: C++ | U3: 9.4 | V3: Submission 1037856937 | W3: Open code | X3: 0 | Y3: 2023-03
A4: 3 | B4: 314 | C4: Binary Tree Vertical Order Traversal | D4: Medium | E4: Binary Tree (BFS / Level Order) | F4: Column BFS | G4: Trees | H4: hash-table, tree, depth-first-search, breadth-first-search, sorting, binary-tree | I4: Ac | J4: 45119.931 | K4: 45119.931 | L4: 45264.395 | M4: 4 | N4: 2 | O4: 1 | P4: =IF(AND(N4>0,O4=0),"Yes","No") | Q4: 1 | R4: 0 | S4: 0 | T4: Python3 | U4: 0.1 | V4: Submission 1111892126 | W4: Open code | X4: 0 | Y4: 2023-07
A5: 4 | B5: 1768 | C5: Merge Strings Alternately | D5: Easy | E5: Two Pointers | F5: Interleave | G5: Arrays & Strings | H5: two-pointers, string | J5: 45155.995 | K5: 45155.995 | L5: 45155.995 | M5: 1 | N5: 1 | O5: 0 | P5: =IF(AND(N5>0,O5=0),"Yes","No") | Q5: 0 | R5: 0 | S5: 0 | T5: C++ | U5: 30.1 | V5: Submission 1024218483 | W5: Open code | X5: 0 | Y5: 2023-08
A6: 5 | B6: 1071 | C6: Greatest Common Divisor of Strings | D6: Easy | E6: Math & Bit Manipulation | F6: GCD | G6: Arrays & Strings | H6: math, string, euclidean-algorithm, greatest-common-divisor | J6: 45156.032 | K6: 45156.033 | L6: 45156.033 | M6: 2 | N6: 1 | O6: 1 | P6: =IF(AND(N6>0,O6=0),"Yes","No") | Q6: 1 | R6: 0 | S6: 0 | T6: C++ | U6: 5.1 | V6: Submission 1024263824 | W6: Open code | X6: 0 | Y6: 2023-08
A7: 6 | B7: 1431 | C7: Kids With the Greatest Number of Candies | D7: Easy | E7: Arrays, Hashing & Sorting | F7: Max scan | G7: Arrays & Strings | H7: array | J7: 45156.915 | K7: 45156.915 | L7: 45156.915 | M7: 1 | N7: 1 | O7: 0 | P7: =IF(AND(N7>0,O7=0),"Yes","No") | Q7: 0 | R7: 0 | S7: 0 | T7: C++ | U7: 100 | V7: Submission 1025007443 | W7: Open code | X7: 0 | Y7: 2023-08
A8: 7 | B8: 605 | C8: Can Place Flowers | D8: Easy | E8: Greedy | F8: Greedy placement | G8: Greedy | H8: array, greedy | J8: 45156.952 | K8: 45156.994 | L8: 45156.994 | M8: 3 | N8: 1 | O8: 2 | P8: =IF(AND(N8>0,O8=0),"Yes","No") | Q8: 1 | R8: 1 | S8: 0 | T8: C++ | U8: 2.9 | V8: Submission 1025106754 | W8: Open code | X8: 0 | Y8: 2023-08
A9: 8 | B9: 345 | C9: Reverse Vowels of a String | D9: Easy | E9: Two Pointers | F9: Opposite ends | G9: Arrays & Strings | H9: two-pointers, string | J9: 45157.01 | K9: 45157.011 | L9: 45157.011 | M9: 2 | N9: 1 | O9: 1 | P9: =IF(AND(N9>0,O9=0),"Yes","No") | Q9: 1 | R9: 0 | S9: 0 | T9: C++ | U9: 32.3 | V9: Submission 1025126413 | W9: Open code | X9: 0 | Y9: 2023-08
A10: 9 | B10: 151 | C10: Reverse Words in a String | D10: Medium | E10: Two Pointers | F10: Reverse words | G10: Arrays & Strings | H10: two-pointers, string | J10: 45161.815 | K10: 45161.815 | L10: 45161.815 | M10: 1 | N10: 1 | O10: 0 | P10: =IF(AND(N10>0,O10=0),"Yes","No") | Q10: 0 | R10: 0 | S10: 0 | T10: C++ | U10: 13.4 | V10: Submission 1029596542 | W10: Open code | X10: 0 | Y10: 2023-08
A11: 10 | B11: 238 | C11: Product of Array Except Self | D11: Medium | E11: Prefix Sum & Difference Array | F11: Prefix/suffix product | G11: Arrays & Strings | H11: array, prefix-sum | I11: Ac | J11: 45161.831 | K11: 45161.831 | L11: 45161.835 | M11: 2 | N11: 2 | O11: 0 | P11: =IF(AND(N11>0,O11=0),"Yes","No") | Q11: 0 | R11: 0 | S11: 0 | T11: C++ | U11: 6.2 | V11: Submission 1029620534 | W11: Open code | X11: 0 | Y11: 2023-08
A12: 11 | B12: 334 | C12: Increasing Triplet Subsequence | D12: Medium | E12: Greedy | F12: Two running minimums | G12: Greedy | H12: array, greedy, longest-increasing-subsequence | J12: 45161.852 | K12: 45161.855 | L12: 45161.862 | M12: 4 | N12: 2 | O12: 1 | P12: =IF(AND(N12>0,O12=0),"Yes","No") | Q12: 1 | R12: 0 | S12: 0 | T12: C++ | U12: 5 | V12: Submission 1029652848 | W12: Open code | X12: 0 | Y12: 2023-08
A13: 12 | B13: 443 | C13: String Compression | D13: Medium | E13: Two Pointers | F13: Read/write pointers | G13: Arrays & Strings | H13: two-pointers, string | J13: 45162.006 | K13: 45162.027 | L13: 45162.032 | M13: 7 | N13: 2 | O13: 5 | P13: =IF(AND(N13>0,O13=0),"Yes","No") | Q13: 5 | R13: 0 | S13: 0 | T13: C++ | U13: 2.3 | V13: Submission 1029879136 | W13: Open code | X13: 0 | Y13: 2023-08
A14: 13 | B14: 283 | C14: Move Zeroes | D14: Easy | E14: Two Pointers | F14: Read/write pointers | G14: Arrays & Strings | H14: array, two-pointers | I14: Ac | J14: 45162.938 | K14: 45162.938 | L14: 45265.109 | M14: 13 | N14: 10 | O14: 0 | P14: =IF(AND(N14>0,O14=0),"Yes","No") | Q14: 0 | R14: 0 | S14: 0 | T14: C++, Python, Python3 | U14: 10.2 | V14: Submission 1112443699 | W14: Open code | X14: 0 | Y14: 2023-08
A15: 14 | B15: 392 | C15: Is Subsequence | D15: Easy | E15: Two Pointers | F15: Subsequence scan | G15: Arrays & Strings | H15: two-pointers, string, dynamic-programming | I15: Ac | J15: 45162.945 | K15: 45162.946 | L15: 45162.946 | M15: 2 | N15: 1 | O15: 1 | P15: =IF(AND(N15>0,O15=0),"Yes","No") | Q15: 1 | R15: 0 | S15: 0 | T15: C++ | U15: 4.7 | V15: Submission 1030693648 | W15: Open code | X15: 0 | Y15: 2023-08
A16: 15 | B16: 11 | C16: Container With Most Water | D16: Medium | E16: Two Pointers | F16: Opposite ends | G16: Arrays & Strings | H16: array, two-pointers, greedy | I16: Ac | J16: 45162.977 | K16: 45162.977 | L16: 45162.977 | M16: 1 | N16: 1 | O16: 0 | P16: =IF(AND(N16>0,O16=0),"Yes","No") | Q16: 0 | R16: 0 | S16: 0 | T16: C++ | U16: 6.1 | V16: Submission 1030734523 | W16: Open code | X16: 0 | Y16: 2023-08
A17: 16 | B17: 1679 | C17: Max Number of K-Sum Pairs | D17: Medium | E17: Two Pointers | F17: Sort + two pointers | G17: Arrays & Strings | H17: array, hash-table, two-pointers, sorting | I17: Ac | J17: 45162.989 | K17: 45162.991 | L17: 45162.991 | M17: 2 | N17: 1 | O17: 1 | P17: =IF(AND(N17>0,O17=0),"Yes","No") | Q17: 1 | R17: 0 | S17: 0 | T17: C++ | U17: 5.1 | V17: Submission 1030753639 | W17: Open code | X17: 0 | Y17: 2023-08
A18: 17 | B18: 643 | C18: Maximum Average Subarray I | D18: Easy | E18: Sliding Window | F18: Fixed window | G18: Arrays & Strings | H18: array, sliding-window | I18: Ac | J18: 45163.006 | K18: 45163.006 | L18: 45248.27 | M18: 2 | N18: 2 | O18: 0 | P18: =IF(AND(N18>0,O18=0),"Yes","No") | Q18: 0 | R18: 0 | S18: 0 | T18: C++, Python3 | U18: 7.6 | V18: Submission 1101111135 | W18: Open code | X18: 0 | Y18: 2023-08
A19: 18 | B19: 1456 | C19: Maximum Number of Vowels in a Substring of Given Length | D19: Medium | E19: Sliding Window | F19: Fixed window | G19: Arrays & Strings | H19: string, sliding-window | J19: 45163.942 | K19: 45163.942 | L19: 45163.947 | M19: 6 | N19: 6 | O19: 0 | P19: =IF(AND(N19>0,O19=0),"Yes","No") | Q19: 0 | R19: 0 | S19: 0 | T19: C++ | U19: 6.2 | V19: Submission 1031598078 | W19: Open code | X19: 0 | Y19: 2023-08
A20: 19 | B20: 1004 | C20: Max Consecutive Ones III | D20: Medium | E20: Sliding Window | F20: At most k zeros | G20: Arrays & Strings | H20: array, binary-search, sliding-window, prefix-sum | I20: Ac | J20: 45163.983 | K20: 45163.983 | L20: 45318.931 | M20: 4 | N20: 4 | O20: 0 | P20: =IF(AND(N20>0,O20=0),"Yes","No") | Q20: 0 | R20: 0 | S20: 0 | T20: C++, Python3 | U20: 5.8 | V20: Submission 1158417154 | W20: Open code | X20: 0 | Y20: 2023-08
A21: 20 | B21: 1493 | C21: Longest Subarray of 1's After Deleting One Element | D21: Medium | E21: Sliding Window | F21: At most 1 zero | G21: Arrays & Strings | H21: array, dynamic-programming, sliding-window | J21: 45170.874 | K21: 45170.874 | L21: 45170.874 | M21: 1 | N21: 1 | O21: 0 | P21: =IF(AND(N21>0,O21=0),"Yes","No") | Q21: 0 | R21: 0 | S21: 0 | T21: C++ | U21: 6.2 | V21: Submission 1037751435 | W21: Open code | X21: 0 | Y21: 2023-09
A22: 21 | B22: 1732 | C22: Find the Highest Altitude | D22: Easy | E22: Prefix Sum & Difference Array | F22: Running sum | G22: Arrays & Strings | H22: array, prefix-sum | J22: 45170.964 | K22: 45170.964 | L22: 45170.964 | M22: 1 | N22: 1 | O22: 0 | P22: =IF(AND(N22>0,O22=0),"Yes","No") | Q22: 0 | R22: 0 | S22: 0 | T22: C++ | U22: 100 | V22: Submission 1037851819 | W22: Open code | X22: 0 | Y22: 2023-09
A23: 22 | B23: 2215 | C23: Find the Difference of Two Arrays | D23: Easy | E23: Arrays, Hashing & Sorting | F23: Sets | G23: Arrays & Strings | H23: array, hash-table | J23: 45177.701 | K23: 45177.701 | L23: 45177.701 | M23: 1 | N23: 1 | O23: 0 | P23: =IF(AND(N23>0,O23=0),"Yes","No") | Q23: 0 | R23: 0 | S23: 0 | T23: C++ | U23: 5 | V23: Submission 1043842772 | W23: Open code | X23: 0 | Y23: 2023-09
A24: 23 | B24: 1207 | C24: Unique Number of Occurrences | D24: Easy | E24: Arrays, Hashing & Sorting | F24: Counting | G24: Arrays & Strings | H24: array, hash-table | J24: 45177.962 | K24: 45177.962 | L24: 45177.962 | M24: 1 | N24: 1 | O24: 0 | P24: =IF(AND(N24>0,O24=0),"Yes","No") | Q24: 0 | R24: 0 | S24: 0 | T24: C++ | U24: 100 | V24: Submission 1044102868 | W24: Open code | X24: 0 | Y24: 2023-09
A25: 24 | B25: 2352 | C25: Equal Row and Column Pairs | D25: Medium | E25: Arrays, Hashing & Sorting | F25: Row hash count | G25: Arrays & Strings | H25: array, hash-table, matrix, simulation | J25: 45178.014 | K25: 45178.014 | L25: 45178.014 | M25: 1 | N25: 1 | O25: 0 | P25: =IF(AND(N25>0,O25=0),"Yes","No") | Q25: 0 | R25: 0 | S25: 0 | T25: C++ | U25: 34.8 | V25: Submission 1044163612 | W25: Open code | X25: 0 | Y25: 2023-09
A26: 25 | B26: 2390 | C26: Removing Stars From a String | D26: Medium | E26: Stack | F26: Stack | G26: Stacks & Queues | H26: string, stack, simulation | J26: 45181.837 | K26: 45181.844 | L26: 45181.844 | M26: 2 | N26: 1 | O26: 1 | P26: =IF(AND(N26>0,O26=0),"Yes","No") | Q26: 0 | R26: 0 | S26: 1 | T26: C++ | U26: 0 | V26: Submission 1047537156 | W26: Open code | X26: 0 | Y26: 2023-09
A27: 26 | B27: 735 | C27: Asteroid Collision | D27: Medium | E27: Stack | F27: Collision stack | G27: Stacks & Queues | H27: array, stack, simulation | J27: 45181.855 | K27: 45181.865 | L27: 45181.871 | M27: 3 | N27: 2 | O27: 1 | P27: =IF(AND(N27>0,O27=0),"Yes","No") | Q27: 0 | R27: 0 | S27: 1 | T27: C++ | U27: 5.5 | V27: Submission 1047569035 | W27: Open code | X27: 0 | Y27: 2023-09
A28: 27 | B28: 394 | C28: Decode String | D28: Medium | E28: Stack | F28: Nested decode stack | G28: Stacks & Queues | H28: string, stack, recursion | J28: 45182.008 | K28: 45182.009 | L28: 45182.009 | M28: 2 | N28: 1 | O28: 1 | P28: =IF(AND(N28>0,O28=0),"Yes","No") | Q28: 1 | R28: 0 | S28: 0 | T28: C++ | U28: 0.8 | V28: Submission 1047748694 | W28: Open code | X28: 0 | Y28: 2023-09
A29: 28 | B29: 933 | C29: Number of Recent Calls | D29: Easy | E29: Design | F29: Queue | G29: Design | H29: design, queue, data-stream | J29: 45182.026 | K29: 45182.026 | L29: 45182.026 | M29: 1 | N29: 1 | O29: 0 | P29: =IF(AND(N29>0,O29=0),"Yes","No") | Q29: 0 | R29: 0 | S29: 0 | T29: C++ | U29: 5.7 | V29: Submission 1047767716 | W29: Open code | X29: 0 | Y29: 2023-09
A30: 29 | B30: 408 | C30: Valid Word Abbreviation | D30: Easy | E30: Two Pointers | F30: Two-pointer parse | G30: Arrays & Strings | H30: two-pointers, string | I30: Ac | J30: 45239.167 | K30: 45239.167 | L30: 45303.911 | M30: 2 | N30: 2 | O30: 0 | P30: =IF(AND(N30>0,O30=0),"Yes","No") | Q30: 0 | R30: 0 | S30: 0 | T30: Python3 | U30: 0.4 | V30: Submission 1144355158 | W30: Open code | X30: 0 | Y30: 2023-11
A31: 30 | B31: 339 | C31: Nested List Weight Sum | D31: Medium | E31: Binary Tree (DFS & Recursion) | F31: Recursive depth sum | G31: Trees | H31: depth-first-search, breadth-first-search | I31: Ac | J31: 45240.23 | K31: 45261.133 | L31: 45264.482 | M31: 5 | N31: 2 | O31: 1 | P31: =IF(AND(N31>0,O31=0),"Yes","No") | Q31: 0 | R31: 0 | S31: 1 | T31: Python3 | U31: 0 | V31: Submission 1111957079 | W31: Open code | X31: 0 | Y31: 2023-12
A32: 31 | B32: 827 | C32: Making A Large Island | D32: Hard | E32: Graph: Grid BFS/DFS | F32: Label islands + merge | G32: Graphs | H32: array, depth-first-search, breadth-first-search, union-find, matrix | I32: Ac | J32: 45242.989 | K32: 45243.026 | L32: 45328.3 | M32: 28 | N32: 5 | O32: 3 | P32: =IF(AND(N32>0,O32=0),"Yes","No") | Q32: 0 | R32: 1 | S32: 2 | T32: Python3 | U32: 5 | V32: Submission 1167335012 | W32: Open code | X32: 0 | Y32: 2023-11
A33: 32 | B33: 921 | C33: Minimum Add to Make Parentheses Valid | D33: Medium | E33: Greedy | F33: Balance counter | G33: Greedy | H33: string, stack, greedy, bracket-sequences | I33: Ac | J33: 45243.039 | K33: 45243.039 | L33: 45265.03 | M33: 4 | N33: 4 | O33: 0 | P33: =IF(AND(N33>0,O33=0),"Yes","No") | Q33: 0 | R33: 0 | S33: 0 | T33: Python3 | U33: 0.6 | V33: Submission 1112386888 | W33: Open code | X33: 0 | Y33: 2023-11
A34: 33 | B34: 766 | C34: Toeplitz Matrix | D34: Easy | E34: Strings & Simulation | F34: Matrix scan | G34: Arrays & Strings | H34: array, matrix | I34: Ac | J34: 45244.89 | K34: 45244.89 | L34: 45265.013 | M34: 2 | N34: 2 | O34: 0 | P34: =IF(AND(N34>0,O34=0),"Yes","No") | Q34: 0 | R34: 0 | S34: 0 | T34: Python3 | U34: 4.7 | V34: Submission 1112372456 | W34: Open code | X34: 0 | Y34: 2023-11
A35: 34 | B35: 199 | C35: Binary Tree Right Side View | D35: Medium | E35: Binary Tree (BFS / Level Order) | F35: Last node per level | G35: Trees | H35: tree, depth-first-search, breadth-first-search, binary-tree | I35: Ac | J35: 45245.893 | K35: 45245.893 | L35: 45313.073 | M35: 3 | N35: 3 | O35: 0 | P35: =IF(AND(N35>0,O35=0),"Yes","No") | Q35: 0 | R35: 0 | S35: 0 | T35: Python3 | U35: 0.5 | V35: Submission 1152935407 | W35: Open code | X35: 0 | Y35: 2023-11
A36: 35 | B36: 88 | C36: Merge Sorted Array | D36: Easy | E36: Two Pointers | F36: Merge from the end | G36: Arrays & Strings | H36: array, two-pointers, sorting | I36: Ac | J36: 45246.027 | K36: 45246.027 | L36: 45265.19 | M36: 3 | N36: 3 | O36: 0 | P36: =IF(AND(N36>0,O36=0),"Yes","No") | Q36: 0 | R36: 0 | S36: 0 | T36: Python, Python3 | U36: 3.1 | V36: Submission 1112489517 | W36: Open code | X36: 0 | Y36: 2023-11
A37: 36 | B37: 125 | C37: Valid Palindrome | D37: Easy | E37: Two Pointers | F37: Opposite ends | G37: Arrays & Strings | H37: two-pointers, string | I37: Ac | J37: 45246.198 | K37: 45246.198 | L37: 45326.415 | M37: 3 | N37: 3 | O37: 0 | P37: =IF(AND(N37>0,O37=0),"Yes","No") | Q37: 0 | R37: 0 | S37: 0 | T37: Python, Python3 | U37: 36.1 | V37: Submission 1165501847 | W37: Open code | X37: 0 | Y37: 2023-11
A38: 37 | B38: 670 | C38: Maximum Swap | D38: Medium | E38: Greedy | F38: Last occurrence | G38: Greedy | H38: math, greedy | I38: Ac | J38: 45246.256 | K38: 45253.15 | L38: 45325.116 | M38: 8 | N38: 3 | O38: 3 | P38: =IF(AND(N38>0,O38=0),"Yes","No") | Q38: 3 | R38: 0 | S38: 0 | T38: Python, Python3 | U38: 0 | V38: Submission 1164268995 | W38: Open code | X38: 0 | Y38: 2023-11
A39: 38 | B39: 986 | C39: Interval List Intersections | D39: Medium | E39: Intervals & Sweep Line | F39: Two-pointer intersection | G39: Heaps & Intervals | H39: array, two-pointers, sweep-line | I39: Ac | J39: 45246.853 | K39: 45246.853 | L39: 45332.095 | M39: 3 | N39: 3 | O39: 0 | P39: =IF(AND(N39>0,O39=0),"Yes","No") | Q39: 0 | R39: 0 | S39: 0 | T39: Python, Python3 | U39: 6.1 | V39: Submission 1170940559 | W39: Open code | X39: 0 | Y39: 2023-11
A40: 39 | B40: 296 | C40: Best Meeting Point | D40: Hard | E40: Math & Bit Manipulation | F40: Median | G40: Arrays & Strings | H40: array, math, sorting, matrix | I40: Ac | J40: 45247.051 | K40: 45247.06 | L40: 45327.302 | M40: 5 | N40: 2 | O40: 1 | P40: =IF(AND(N40>0,O40=0),"Yes","No") | Q40: 0 | R40: 1 | S40: 0 | T40: Python, Python3 | U40: 18.2 | V40: Submission 1112468782 | W40: Open code | X40: 0 | Y40: 2023-11
A41: 40 | B41: 480 | C41: Sliding Window Median | D41: Hard | E41: Heap / Top-K | F41: Two heaps with lazy delete | G41: Heaps & Intervals | H41: array, hash-table, sliding-window, heap-priority-queue, treap | I41: Ac | J41: 45248.037 | K41: 45248.038 | L41: 45317.415 | M41: 4 | N41: 3 | O41: 1 | P41: =IF(AND(N41>0,O41=0),"Yes","No") | Q41: 1 | R41: 0 | S41: 0 | T41: Python3 | U41: 6.1 | V41: Submission 1157053663 | W41: Open code | X41: 0 | Y41: 2023-11
A42: 41 | B42: 217 | C42: Contains Duplicate | D42: Easy | E42: Arrays, Hashing & Sorting | F42: Hash set | G42: Arrays & Strings | H42: array, hash-table, sorting | I42: Notac | J42: 45248.11 | L42: 45248.11 | M42: 1 | N42: 0 | O42: 1 | P42: =IF(AND(N42>0,O42=0),"Yes","No") | Q42: 0 | R42: 1 | S42: 0 | T42: Python3 | W42: Open code | X42: 0
A43: 42 | B43: 219 | C43: Contains Duplicate II | D43: Easy | E43: Sliding Window | F43: Window set | G43: Arrays & Strings | H43: array, hash-table, sliding-window | I43: Ac | J43: 45248.115 | K43: 45248.115 | L43: 45248.115 | M43: 1 | N43: 1 | O43: 0 | P43: =IF(AND(N43>0,O43=0),"Yes","No") | Q43: 0 | R43: 0 | S43: 0 | T43: Python3 | U43: 5 | V43: Submission 1101040393 | W43: Open code | X43: 0 | Y43: 2023-11
A44: 43 | B44: 347 | C44: Top K Frequent Elements | D44: Medium | E44: Heap / Top-K | F44: Top-K / bucket sort | G44: Heaps & Intervals | H44: array, hash-table, divide-and-conquer, sorting, heap-priority-queue, bucket-sort, counting, quickselect | I44: Ac | J44: 45249.377 | K44: 45249.382 | L44: 45306.302 | M44: 9 | N44: 4 | O44: 4 | P44: =IF(AND(N44>0,O44=0),"Yes","No") | Q44: 4 | R44: 0 | S44: 0 | T44: Python3 | U44: 5 | V44: Submission 1146455372 | W44: Open code | X44: 0 | Y44: 2023-11
A45: 44 | B45: 490 | C45: The Maze | D45: Medium | E45: Graph: Grid BFS/DFS | F45: Rolling BFS | G45: Graphs | H45: array, depth-first-search, breadth-first-search, matrix | I45: Ac | J45: 45249.861 | K45: 45249.866 | L45: 45249.866 | M45: 2 | N45: 1 | O45: 1 | P45: =IF(AND(N45>0,O45=0),"Yes","No") | Q45: 1 | R45: 0 | S45: 0 | T45: Python3 | U45: 5.2 | V45: Submission 1102138705 | W45: Open code | X45: 0 | Y45: 2023-11
A46: 45 | B46: 1011 | C46: Capacity To Ship Packages Within D Days | D46: Medium | E46: Binary Search on Answer | F46: Minimise capacity | G46: Searching | H46: array, binary-search | I46: Ac | J46: 45250.058 | K46: 45250.058 | L46: 45257.839 | M46: 2 | N46: 2 | O46: 0 | P46: =IF(AND(N46>0,O46=0),"Yes","No") | Q46: 0 | R46: 0 | S46: 0 | T46: Python3 | U46: 5.7 | V46: Submission 1107477954 | W46: Open code | X46: 0 | Y46: 2023-11
A47: 46 | B47: 215 | C47: Kth Largest Element in an Array | D47: Medium | E47: Heap / Top-K | F47: Quickselect / heap | G47: Heaps & Intervals | H47: array, divide-and-conquer, sorting, heap-priority-queue, quickselect | I47: Ac | J47: 45250.842 | K47: 45250.842 | L47: 45523.275 | M47: 6 | N47: 2 | O47: 1 | P47: =IF(AND(N47>0,O47=0),"Yes","No") | Q47: 0 | R47: 1 | S47: 0 | T47: Java, Python3 | U47: 64 | V47: Submission 1360851507 | W47: Open code | X47: 0 | Y47: 2023-11
A48: 47 | B48: 1249 | C48: Minimum Remove to Make Valid Parentheses | D48: Medium | E48: Stack | F48: Index stack | G48: Stacks & Queues | H48: string, stack | I48: Ac | J48: 45251.21 | K48: 45251.21 | L48: 45854.518 | M48: 5 | N48: 4 | O48: 0 | P48: =IF(AND(N48>0,O48=0),"Yes","No") | Q48: 0 | R48: 0 | S48: 0 | T48: C++, Python3 | U48: 77.5 | V48: Submission 1699732158 | W48: Open code | X48: 0 | Y48: 2023-11
A49: 48 | B49: 1650 | C49: Lowest Common Ancestor of a Binary Tree III | D49: Medium | E49: Binary Tree (DFS & Recursion) | F49: Parent pointers, two-pointer | G49: Trees | H49: hash-table, two-pointers, tree, binary-tree, binary-lifting, lowest-common-ancestor | I49: Ac | J49: 45251.894 | K49: 45251.894 | L49: 45303.928 | M49: 4 | N49: 4 | O49: 0 | P49: =IF(AND(N49>0,O49=0),"Yes","No") | Q49: 0 | R49: 0 | S49: 0 | T49: Python3 | U49: 99.1 | V49: Submission 1144374104 | W49: Open code | X49: 0 | Y49: 2023-11
A50: 49 | B50: 415 | C50: Add Strings | D50: Easy | E50: Strings & Simulation | F50: Digit addition | G50: Arrays & Strings | H50: math, string, simulation | I50: Ac | J50: 45252.063 | K50: 45252.063 | L50: 45313.047 | M50: 5 | N50: 3 | O50: 0 | P50: =IF(AND(N50>0,O50=0),"Yes","No") | Q50: 0 | R50: 0 | S50: 0 | T50: Python3 | U50: 8.3 | V50: Submission 1152910148 | W50: Open code | X50: 0 | Y50: 2023-11
A51: 50 | B51: 67 | C51: Add Binary | D51: Easy | E51: Strings & Simulation | F51: Digit addition | G51: Arrays & Strings | H51: math, string, bit-manipulation, simulation | I51: Ac | J51: 45252.082 | K51: 45252.082 | L51: 45252.082 | M51: 2 | N51: 2 | O51: 0 | P51: =IF(AND(N51>0,O51=0),"Yes","No") | Q51: 0 | R51: 0 | S51: 0 | T51: Python3 | U51: 4.7 | V51: Submission 1103721779 | W51: Open code | X51: 0 | Y51: 2023-11
A52: 51 | B52: 708 | C52: Insert into a Sorted Circular Linked List | D52: Medium | E52: Linked List | F52: Circular insert | G52: Linked List | H52: linked-list | I52: Ac | J52: 45253.056 | K52: 45253.062 | L52: 45291.052 | M52: 7 | N52: 3 | O52: 1 | P52: =IF(AND(N52>0,O52=0),"Yes","No") | Q52: 1 | R52: 0 | S52: 0 | T52: Python3 | U52: 93.8 | V52: Submission 1132452299 | W52: Open code | X52: 0 | Y52: 2023-11
A53: 52 | B53: 426 | C53: Convert Binary Search Tree to Sorted Doubly Linked List | D53: Medium | E53: Binary Search Tree | F53: Inorder linking | G53: Trees | H53: linked-list, stack, tree, depth-first-search, binary-search-tree, binary-tree, doubly-linked-list | I53: Ac | J53: 45253.091 | K53: 45253.091 | L53: 45304.156 | M53: 6 | N53: 3 | O53: 1 | P53: =IF(AND(N53>0,O53=0),"Yes","No") | Q53: 0 | R53: 0 | S53: 1 | T53: Python3 | U53: 99 | V53: Submission 1144582411 | W53: Open code | X53: 0 | Y53: 2023-11
A54: 53 | B54: 65 | C54: Valid Number | D54: Hard | E54: Strings & Simulation | F54: Parsing / state machine | G54: Arrays & Strings | H54: string | I54: Ac | J54: 45253.142 | K54: 45253.142 | L54: 45332.037 | M54: 7 | N54: 4 | O54: 0 | P54: =IF(AND(N54>0,O54=0),"Yes","No") | Q54: 0 | R54: 0 | S54: 0 | T54: Python3 | U54: 3.8 | V54: Submission 1170890636 | W54: Open code | X54: 0 | Y54: 2023-11
... A59: 58 | B59: 348 | C59: Design Tic-Tac-Toe | D59: Medium | E59: Design | F59: Row/column counters | G59: Design | H59: array, hash-table, design, matrix, simulation | I59: Ac | J59: 45254.837 | K59: 45254.837 | L59: 45285.127 | M59: 7 | N59: 4 | O59: 1 | P59: =IF(AND(N59>0,O59=0),"Yes","No") | Q59: 0 | R59: 0 | S59: 1 | T59: Python, Python3 | U59: 96.6 | V59: Submission 1127706827 | W59: Open code | X59: 0 | Y59: 2023-11
A60: 59 | B60: 398 | C60: Random Pick Index | D60: Medium | E60: Math & Bit Manipulation | F60: Reservoir sampling | G60: Arrays & Strings | H60: hash-table, math, reservoir-sampling, randomized | I60: Notac | J60: 45255.199 | L60: 45293.058 | M60: 6 | N60: 0 | O60: 6 | P60: =IF(AND(N60>0,O60=0),"Yes","No") | Q60: 0 | R60: 4 | S60: 2 | T60: Python3 | W60: Open code | X60: 0
A61: 60 | B61: 317 | C61: Shortest Distance from All Buildings | D61: Hard | E61: Graph: Grid BFS/DFS | F61: BFS from each building | G61: Graphs | H61: array, breadth-first-search, matrix | I61: Ac | J61: 45256.909 | K61: 45256.956 | L61: 45263.198 | M61: 11 | N61: 5 | O61: 2 | P61: =IF(AND(N61>0,O61=0),"Yes","No") | Q61: 0 | R61: 1 | S61: 1 | T61: Python3 | U61: 28.1 | V61: Submission 1111111437 | W61: Open code | X61: 0 | Y61: 2023-11
A62: 61 | B62: 498 | C62: Diagonal Traverse | D62: Medium | E62: Strings & Simulation | F62: Matrix simulation | G62: Arrays & Strings | H62: array, matrix, simulation | I62: Ac | J62: 45256.964 | K62: 45256.964 | L62: 45265.101 | M62: 3 | N62: 3 | O62: 0 | P62: =IF(AND(N62>0,O62=0),"Yes","No") | Q62: 0 | R62: 0 | S62: 0 | T62: Python3 | U62: 8.4 | V62: Submission 1112438365 | W62: Open code | X62: 0 | Y62: 2023-11
A63: 62 | B63: 953 | C63: Verifying an Alien Dictionary | D63: Easy | E63: Arrays, Hashing & Sorting | F63: Rank map compare | G63: Arrays & Strings | H63: array, hash-table, string | I63: Ac | J63: 45257.429 | K63: 45257.437 | L63: 45317.089 | M63: 11 | N63: 2 | O63: 9 | P63: =IF(AND(N63>0,O63=0),"Yes","No") | Q63: 9 | R63: 0 | S63: 0 | T63: Python3 | U63: 1.2 | V63: Submission 1156830185 | W63: Open code | X63: 0 | Y63: 2023-11
A64: 63 | B64: 1891 | C64: Cutting Ribbons | D64: Medium | E64: Binary Search on Answer | F64: Maximise length | G64: Searching | H64: array, binary-search | I64: Ac | J64: 45257.893 | K64: 45257.904 | L64: 45332.962 | M64: 9 | N64: 1 | O64: 6 | P64: =IF(AND(N64>0,O64=0),"Yes","No") | Q64: 6 | R64: 0 | S64: 0 | T64: Python3 | U64: 5.3 | V64: Submission 1107532903 | W64: Open code | X64: 0 | Y64: 2023-11
A65: 64 | B65: 1541 | C65: Minimum Insertions to Balance a Parentheses String | D65: Medium | E65: Greedy | F65: Balance counter | G65: Greedy | H65: string, stack, greedy, bracket-sequences | I65: Ac | J65: 45258.28 | K65: 45258.28 | L65: 45258.28 | M65: 1 | N65: 1 | O65: 0 | P65: =IF(AND(N65>0,O65=0),"Yes","No") | Q65: 0 | R65: 0 | S65: 0 | T65: Python3 | U65: 5.1 | V65: Submission 1107805104 | W65: Open code | X65: 0 | Y65: 2023-11
A66: 65 | B66: 1216 | C66: Valid Palindrome III | D66: Hard | E66: DP: Strings (LCS, Edit, Matching) | F66: Via longest palindromic subsequence | G66: Dynamic Programming | H66: string, dynamic-programming | I66: Ac | J66: 45258.31 | K66: 45258.344 | L66: 45296.5 | M66: 11 | N66: 2 | O66: 7 | P66: =IF(AND(N66>0,O66=0),"Yes","No") | Q66: 5 | R66: 1 | S66: 1 | T66: Python3 | U66: 36.3 | V66: Submission 1112482609 | W66: Open code | X66: 0 | Y66: 2023-11
A67: 66 | B67: 304 | C67: Range Sum Query 2D - Immutable | D67: Medium | E67: Prefix Sum & Difference Array | F67: 2D prefix sum | G67: Arrays & Strings | H67: array, design, matrix, prefix-sum | I67: Ac | J67: 45260.023 | L67: 45260.023 | M67: 1 | N67: 0 | O67: 1 | P67: =IF(AND(N67>0,O67=0),"Yes","No") | Q67: 1 | R67: 0 | S67: 0 | T67: Python3 | W67: Open code | X67: 0
A68: 67 | B68: 295 | C68: Find Median from Data Stream | D68: Hard | E68: Heap / Top-K | F68: Two heaps | G68: Heaps & Intervals | H68: two-pointers, design, sorting, heap-priority-queue, data-stream | I68: Ac | J68: 45260.237 | K68: 45260.237 | L68: 45333.338 | M68: 4 | N68: 4 | O68: 0 | P68: =IF(AND(N68>0,O68=0),"Yes","No") | Q68: 0 | R68: 0 | S68: 0 | T68: Python3 | U68: 11.8 | V68: Submission 1171872574 | W68: Open code | X68: 0 | Y68: 2023-11
A69: 68 | B69: 1186 | C69: Maximum Subarray Sum with One Deletion | D69: Medium | E69: DP: 1D / Linear | F69: Kadane with state | G69: Dynamic Programming | H69: array, dynamic-programming | I69: Ac | J69: 45260.446 | K69: 45260.447 | L69: 45332.949 | M69: 6 | N69: 4 | O69: 1 | P69: =IF(AND(N69>0,O69=0),"Yes","No") | Q69: 0 | R69: 0 | S69: 1 | T69: Python3 | U69: 5 | V69: Submission 1171581598 | W69: Open code | X69: 0 | Y69: 2023-11
A70: 69 | B70: 1570 | C70: Dot Product of Two Sparse Vectors | D70: Medium | E70: Design | F70: Sparse map | G70: Design | H70: array, hash-table, two-pointers, design, linear-algebra | I70: Ac | J70: 45261.146 | K70: 45261.149 | L70: 45261.149 | M70: 2 | N70: 1 | O70: 1 | P70: =IF(AND(N70>0,O70=0),"Yes","No") | Q70: 0 | R70: 0 | S70: 1 | T70: Python3 | U70: 5.1 | V70: Submission 1109825198 | W70: Open code | X70: 0 | Y70: 2023-12
A71: 70 | B71: 249 | C71: Group Shifted Strings | D71: Medium | E71: Arrays, Hashing & Sorting | F71: Canonical key | G71: Arrays & Strings | H71: array, hash-table, string | I71: Ac | J71: 45261.401 | K71: 45261.401 | L71: 45264.875 | M71: 2 | N71: 2 | O71: 0 | P71: =IF(AND(N71>0,O71=0),"Yes","No") | Q71: 0 | R71: 0 | S71: 0 | T71: Python3 | U71: 4.6 | V71: Submission 1112242328 | W71: Open code | X71: 0 | Y71: 2023-12
A72: 71 | B72: 825 | C72: Friends Of Appropriate Ages | D72: Medium | E72: Arrays, Hashing & Sorting | F72: Count buckets | G72: Arrays & Strings | H72: array, two-pointers, binary-search, sorting | I72: Ac | J72: 45264.016 | K72: 45264.016 | L72: 45316.968 | M72: 2 | N72: 2 | O72: 0 | P72: =IF(AND(N72>0,O72=0),"Yes","No") | Q72: 0 | R72: 0 | S72: 0 | T72: Python3 | U72: 6.2 | V72: Submission 1156696705 | W72: Open code | X72: 0 | Y72: 2023-12
A73: 72 | B73: 791 | C73: Custom Sort String | D73: Medium | E73: Arrays, Hashing & Sorting | F73: Counting sort | G73: Arrays & Strings | H73: hash-table, string, sorting | I73: Ac | J73: 45264.495 | K73: 45264.495 | L73: 45325.955 | M73: 5 | N73: 5 | O73: 0 | P73: =IF(AND(N73>0,O73=0),"Yes","No") | Q73: 0 | R73: 0 | S73: 0 | T73: Python3 | U73: 0.8 | V73: Submission 1165073106 | W73: Open code | X73: 0 | Y73: 2023-12
A74: 73 | B74: 691 | C74: Stickers to Spell Word | D74: Hard | E74: DP: Bitmask | F74: Memo over remaining letters | G74: Dynamic Programming | H74: array, hash-table, string, dynamic-programming, backtracking, bit-manipulation, memoization, bitmask | I74: Ac | J74: 45264.533 | K74: 45264.539 | L74: 45325.111 | M74: 29 | N74: 14 | O74: 4 | P74: =IF(AND(N74>0,O74=0),"Yes","No") | Q74: 4 | R74: 0 | S74: 0 | T74: Python3 | U74: 46.1 | V74: Submission 1164265403 | W74: Open code | X74: 0 | Y74: 2023-12
A75: 74 | B75: 282 | C75: Expression Add Operators | D75: Hard | E75: Backtracking | F75: Operator insertion | G75: Recursion & Backtracking | H75: math, string, backtracking | I75: Ac | J75: 45265.185 | K75: 45265.185 | L75: 45289.973 | M75: 5 | N75: 4 | O75: 0 | P75: =IF(AND(N75>0,O75=0),"Yes","No") | Q75: 0 | R75: 0 | S75: 0 | T75: Python3 | U75: 39.1 | V75: Submission 1131582212 | W75: Open code | X75: 0 | Y75: 2023-12
A76: 75 | B76: 38 | C76: Count and Say | D76: Medium | E76: Strings & Simulation | F76: Simulation | G76: Arrays & Strings | H76: string | I76: Ac | J76: 45271.17 | K76: 45271.17 | L76: 45293.15 | M76: 3 | N76: 2 | O76: 1 | P76: =IF(AND(N76>0,O76=0),"Yes","No") | Q76: 0 | R76: 0 | S76: 1 | T76: Python3 | U76: 18.8 | V76: Submission 1134094340 | W76: Open code | X76: 0 | Y76: 2023-12
A77: 76 | B77: 1424 | C77: Diagonal Traverse II | D77: Medium | E77: Arrays, Hashing & Sorting | F77: Group by i+j | G77: Arrays & Strings | H77: array, sorting, heap-priority-queue | I77: Ac | J77: 45271.222 | K77: 45271.222 | L77: 45318.388 | M77: 2 | N77: 2 | O77: 0 | P77: =IF(AND(N77>0,O77=0),"Yes","No") | Q77: 0 | R77: 0 | S77: 0 | T77: Python3 | U77: 5.3 | V77: Submission 1157919798 | W77: Open code | X77: 0 | Y77: 2023-12
A78: 77 | B78: 1522 | C78: Diameter of N-Ary Tree | D78: Medium | E78: DP: On Trees | F78: Top-2 heights | G78: Dynamic Programming | H78: tree, depth-first-search, dp-on-trees | I78: Ac | J78: 45271.885 | K78: 45271.885 | L78: 45271.885 | M78: 1 | N78: 1 | O78: 0 | P78: =IF(AND(N78>0,O78=0),"Yes","No") | Q78: 0 | R78: 0 | S78: 0 | T78: Python3 | U78: 92.2 | V78: Submission 1117330803 | W78: Open code | X78: 0 | Y78: 2023-12
A79: 78 | B79: 1060 | C79: Missing Element in Sorted Array | D79: Medium | E79: Binary Search | F79: Missing-count search | G79: Searching | H79: array, binary-search | I79: Ac | J79: 45272.044 | K79: 45272.044 | L79: 45315.388 | M79: 4 | N79: 3 | O79: 1 | P79: =IF(AND(N79>0,O79=0),"Yes","No") | Q79: 1 | R79: 0 | S79: 0 | T79: Python3 | U79: 5.8 | V79: Submission 1155179452 | W79: Open code | X79: 0 | Y79: 2023-12
... A96: 95 | B96: 1944 | C96: Number of Visible People in a Queue | D96: Hard | E96: Monotonic Stack / Deque | F96: Monotonic stack | G96: Stacks & Queues | H96: array, stack, monotonic-stack | I96: Ac | J96: 45314.452 | K96: 45314.452 | L96: 45333.014 | M96: 4 | N96: 4 | O96: 0 | P96: =IF(AND(N96>0,O96=0),"Yes","No") | Q96: 0 | R96: 0 | S96: 0 | T96: Python3 | U96: 5.1 | V96: Submission 1171657448 | W96: Open code | X96: 0 | Y96: 2024-01
A97: 96 | B97: 2365 | C97: Task Scheduler II | D97: Medium | E97: Arrays, Hashing & Sorting | F97: Last-day map | G97: Arrays & Strings | H97: array, hash-table, simulation | I97: Notac | J97: 45317.175 | L97: 45317.175 | M97: 1 | N97: 0 | O97: 1 | P97: =IF(AND(N97>0,O97=0),"Yes","No") | Q97: 0 | R97: 1 | S97: 0 | T97: Python3 | W97: Open code | X97: 0
A98: 97 | B98: 163 | C98: Missing Ranges | D98: Easy | E98: Arrays, Hashing & Sorting | F98: Gap scan | G98: Arrays & Strings | H98: array | I98: Ac | J98: 45318.061 | K98: 45318.063 | L98: 45332.99 | M98: 8 | N98: 5 | O98: 2 | P98: =IF(AND(N98>0,O98=0),"Yes","No") | Q98: 2 | R98: 0 | S98: 0 | T98: Python3 | U98: 0 | V98: Submission 1171631028 | W98: Open code | X98: 0 | Y98: 2024-01
A99: 98 | B99: 692 | C99: Top K Frequent Words | D99: Medium | E99: Heap / Top-K | F99: Top-K with heap | G99: Heaps & Intervals | H99: array, hash-table, string, trie, sorting, heap-priority-queue, bucket-sort, counting | I99: Notac | J99: 45319.119 | L99: 45319.119 | M99: 1 | N99: 0 | O99: 1 | P99: =IF(AND(N99>0,O99=0),"Yes","No") | Q99: 1 | R99: 0 | S99: 0 | T99: Python3 | W99: Open code | X99: 0
A100: 99 | B100: 161 | C100: One Edit Distance | D100: Medium | E100: Two Pointers | F100: Single mismatch | G100: Arrays & Strings | H100: two-pointers, string | I100: Ac | J100: 45320.223 | K100: 45320.23 | L100: 45320.23 | M100: 4 | N100: 1 | O100: 3 | P100: =IF(AND(N100>0,O100=0),"Yes","No") | Q100: 1 | R100: 0 | S100: 2 | T100: Python3 | U100: 5.7 | V100: Submission 1159609851 | W100: Open code | X100: 0 | Y100: 2024-01
A101: 100 | B101: 536 | C101: Construct Binary Tree from String | D101: Medium | E101: Binary Tree (DFS & Recursion) | F101: Recursive parsing | G101: Trees | H101: string, stack, tree, depth-first-search, binary-tree | I101: Ac | J101: 45321.175 | K101: 45321.176 | L101: 45321.176 | M101: 2 | N101: 1 | O101: 1 | P101: =IF(AND(N101>0,O101=0),"Yes","No") | Q101: 0 | R101: 0 | S101: 1 | T101: Python3 | U101: 6.6 | V101: Submission 1160501419 | W101: Open code | X101: 0 | Y101: 2024-01
A102: 101 | B102: 689 | C102: Maximum Sum of 3 Non-Overlapping Subarrays | D102: Hard | E102: Prefix Sum & Difference Array | F102: Prefix sum + best left/right | G102: Arrays & Strings | H102: array, dynamic-programming, sliding-window, prefix-sum | I102: Notac | J102: 45326.491 | L102: 45326.491 | M102: 1 | N102: 0 | O102: 1 | P102: =IF(AND(N102>0,O102=0),"Yes","No") | Q102: 1 | R102: 0 | S102: 0 | T102: Python3 | W102: Open code | X102: 0
A103: 102 | B103: 18 | C103: 4Sum | D103: Medium | E103: Two Pointers | F103: Sort + two pointers | G103: Arrays & Strings | H103: array, two-pointers, sorting | I103: Ac | J103: 45328.248 | K103: 45328.249 | L103: 45332.172 | M103: 4 | N103: 2 | O103: 1 | P103: =IF(AND(N103>0,O103=0),"Yes","No") | Q103: 1 | R103: 0 | S103: 0 | T103: Python3 | U103: 17.7 | V103: Submission 1167304301 | W103: Open code | X103: 0 | Y103: 2024-02
A104: 103 | B104: 1382 | C104: Balance a Binary Search Tree | D104: Medium | E104: Binary Search Tree | F104: Inorder + rebuild | G104: Trees | H104: divide-and-conquer, greedy, tree, depth-first-search, binary-search-tree, binary-tree | I104: Ac | J104: 45328.453 | K104: 45328.453 | L104: 45328.453 | M104: 1 | N104: 1 | O104: 0 | P104: =IF(AND(N104>0,O104=0),"Yes","No") | Q104: 0 | R104: 0 | S104: 0 | T104: Python3 | U104: 6.2 | V104: Submission 1167477754 | W104: Open code | X104: 0 | Y104: 2024-02
A105: 104 | B105: 2265 | C105: Count Nodes Equal to Average of Subtree | D105: Medium | E105: Binary Tree (DFS & Recursion) | F105: Postorder aggregate | G105: Trees | H105: tree, depth-first-search, binary-tree | I105: Ac | J105: 45328.464 | K105: 45328.464 | L105: 45328.464 | M105: 1 | N105: 1 | O105: 0 | P105: =IF(AND(N105>0,O105=0),"Yes","No") | Q105: 0 | R105: 0 | S105: 0 | T105: Python3 | U105: 77.5 | V105: Submission 1167489848 | W105: Open code | X105: 0 | Y105: 2024-02
A106: 105 | B106: 1161 | C106: Maximum Level Sum of a Binary Tree | D106: Medium | E106: Binary Tree (BFS / Level Order) | F106: Level order | G106: Trees | H106: tree, depth-first-search, breadth-first-search, binary-tree | I106: Ac | J106: 45328.538 | K106: 45328.538 | L106: 45329.071 | M106: 3 | N106: 2 | O106: 1 | P106: =IF(AND(N106>0,O106=0),"Yes","No") | Q106: 1 | R106: 0 | S106: 0 | T106: Python3 | U106: 5.2 | V106: Submission 1168161300 | W106: Open code | X106: 0 | Y106: 2024-02
A107: 106 | B107: 1644 | C107: Lowest Common Ancestor of a Binary Tree II | D107: Medium | E107: Binary Tree (DFS & Recursion) | F107: LCA with existence check | G107: Trees | H107: tree, depth-first-search, binary-tree, binary-lifting, lowest-common-ancestor | I107: Ac | J107: 45328.542 | K107: 45328.542 | L107: 45332.625 | M107: 3 | N107: 3 | O107: 0 | P107: =IF(AND(N107>0,O107=0),"Yes","No") | Q107: 0 | R107: 0 | S107: 0 | T107: Python3 | U107: 86.1 | V107: Submission 1171287329 | W107: Open code | X107: 0 | Y107: 2024-02
A108: 107 | B108: 111 | C108: Minimum Depth of Binary Tree | D108: Easy | E108: Binary Tree (BFS / Level Order) | F108: BFS to first leaf | G108: Trees | H108: tree, depth-first-search, breadth-first-search, binary-tree | I108: Ac | J108: 45328.556 | K108: 45328.557 | L108: 45328.557 | M108: 3 | N108: 1 | O108: 2 | P108: =IF(AND(N108>0,O108=0),"Yes","No") | Q108: 0 | R108: 0 | S108: 2 | T108: Python3 | U108: 5.2 | V108: Submission 1167590796 | W108: Open code | X108: 0 | Y108: 2024-02
A109: 108 | B109: 865 | C109: Smallest Subtree with all the Deepest Nodes | D109: Medium | E109: Binary Tree (DFS & Recursion) | F109: Depth + LCA | G109: Trees | H109: hash-table, tree, depth-first-search, breadth-first-search, binary-tree, binary-lifting, lowest-common-ancestor, dp-on-trees | I109: Ac | J109: 45328.898 | K109: 45328.898 | L109: 45328.898 | M109: 1 | N109: 1 | O109: 0 | P109: =IF(AND(N109>0,O109=0),"Yes","No") | Q109: 0 | R109: 0 | S109: 0 | T109: Python3 | U109: 1.5 | V109: Submission 1167935171 | W109: Open code | X109: 0 | Y109: 2024-02
A110: 109 | B110: 904 | C110: Fruit Into Baskets | D110: Medium | E110: Sliding Window | F110: At most 2 distinct | G110: Arrays & Strings | H110: array, hash-table, sliding-window | I110: Ac | J110: 45332.609 | K110: 45332.609 | L110: 45332.609 | M110: 1 | N110: 1 | O110: 0 | P110: =IF(AND(N110>0,O110=0),"Yes","No") | Q110: 0 | R110: 0 | S110: 0 | T110: Python3 | U110: 5.1 | V110: Submission 1171274364 | W110: Open code | X110: 0 | Y110: 2024-02
A111: 110 | B111: 2328 | C111: Number of Increasing Paths in a Grid | D111: Hard | E111: DP: Grid / 2D | F111: Memoized DFS on grid | G111: Dynamic Programming | H111: array, dynamic-programming, depth-first-search, breadth-first-search, graph, topological-sort, memoization, matrix | I111: Ac | J111: 45332.656 | K111: 45332.658 | L111: 45332.658 | M111: 2 | N111: 1 | O111: 1 | P111: =IF(AND(N111>0,O111=0),"Yes","No") | Q111: 0 | R111: 0 | S111: 1 | T111: Python3 | U111: 5.1 | V111: Submission 1171314082 | W111: Open code | X111: 0 | Y111: 2024-02
A112: 111 | B112: 103 | C112: Binary Tree Zigzag Level Order Traversal | D112: Medium | E112: Binary Tree (BFS / Level Order) | F112: Level order | G112: Trees | H112: tree, breadth-first-search, binary-tree | I112: Ac | J112: 45332.89 | K112: 45332.89 | L112: 45332.89 | M112: 1 | N112: 1 | O112: 0 | P112: =IF(AND(N112>0,O112=0),"Yes","No") | Q112: 0 | R112: 0 | S112: 0 | T112: Python3 | U112: 0.3 | V112: Submission 1171517062 | W112: Open code | X112: 0 | Y112: 2024-02
A113: 112 | B113: 958 | C113: Check Completeness of a Binary Tree | D113: Medium | E113: Binary Tree (BFS / Level Order) | F113: Level order null check | G113: Trees | H113: tree, breadth-first-search, binary-tree | I113: Ac | J113: 45332.893 | K113: 45332.893 | L113: 45332.893 | M113: 1 | N113: 1 | O113: 0 | P113: =IF(AND(N113>0,O113=0),"Yes","No") | Q113: 0 | R113: 0 | S113: 0 | T113: Python3 | U113: 0.6 | V113: Submission 1171520216 | W113: Open code | X113: 0 | Y113: 2024-02
A114: 113 | B114: 674 | C114: Longest Continuous Increasing Subsequence | D114: Easy | E114: Arrays, Hashing & Sorting | F114: Run scan | G114: Arrays & Strings | H114: array | I114: Ac | J114: 45332.919 | K114: 45332.919 | L114: 45332.919 | M114: 1 | N114: 1 | O114: 0 | P114: =IF(AND(N114>0,O114=0),"Yes","No") | Q114: 0 | R114: 0 | S114: 0 | T114: Python3 | U114: 5.1 | V114: Submission 1171546475 | W114: Open code | X114: 0 | Y114: 2024-02
... A119: 118 | B119: 234 | C119: Palindrome Linked List | D119: Easy | E119: Linked List | F119: Middle + reverse | G119: Linked List | H119: linked-list, two-pointers, stack, recursion | I119: Ac | J119: 46299.428 | K119: 46299.428 | L119: 46299.428 | M119: 1 | N119: 1 | O119: 0 | P119: =IF(AND(N119>0,O119=0),"Yes","No") | Q119: 0 | R119: 0 | S119: 0 | T119: C++ | U119: 48.9 | V119: Submission 2161729892 | W119: Open code | X119: 0 | Y119: 2026-10

Sheet Submissions
A1: Submitted (IST) | B1: Month | C1: LC # | D1: Problem | E1: Difficulty | F1: Pattern | G1: Status | H1: Language | I1: Runtime | J1: Memory | K1: Runtime beats % | L1: Tests passed | M1: Submission | N1: In your list?
A2: 44991.879 | B2: 2023-03 | C2: 1480 | D2: Running Sum of 1d Array | E2: Easy | F2: Prefix Sum & Difference Array | G2: Accepted | H2: C++ | I2: 0 ms | J2: 8.6 MB | K2: 100 | L2: 53/53 | M2: Submission 910238803 | N2: No
A3: 44991.886 | B3: 2023-03 | C3: 724 | D3: Find Pivot Index | E3: Easy | F3: Prefix Sum & Difference Array | G3: Accepted | H3: C++ | I3: 31 ms | J3: 32.3 MB | K3: 9.4 | L3: 746/746 | M3: Submission 910244350 | N3: No
A4: 44991.912 | B4: 2023-03 | C4: 1 | D4: Two Sum | E4: Easy | F4: Arrays, Hashing & Sorting | G4: Accepted | H4: C++ | I4: 9 ms | J4: 11.3 MB | K4: 40.6 | L4: 57/57 | M4: Submission 910266383 | N4: Yes
A5: 44991.914 | B5: 2023-03 | C5: 1 | D5: Two Sum | E5: Easy | F5: Arrays, Hashing & Sorting | G5: Accepted | H5: C++ | I5: 14 ms | J5: 11.1 MB | K5: 39.3 | L5: 57/57 | M5: Submission 910268202 | N5: Yes
A6: 44991.939 | B6: 2023-03 | C6: 13 | D6: Roman to Integer | E6: Easy | F6: Strings & Simulation | G6: Accepted | H6: C++ | I6: 17 ms | J6: 8.6 MB | K6: 5.1 | L6: 3999/3999 | M6: Submission 910290507 | N6: Yes
A7: 44991.944 | B7: 2023-03 | C7: 14 | D7: Longest Common Prefix | E7: Easy | F7: Strings & Simulation | G7: Wrong Answer | H7: C++ | I7: N/A | J7: N/A | L7: 110/124 | M7: Submission 910295360 | N7: Yes
A8: 44991.945 | B8: 2023-03 | C8: 14 | D8: Longest Common Prefix | E8: Easy | F8: Strings & Simulation | G8: Accepted | H8: C++ | I8: 0 ms | J8: 9.2 MB | K8: 100 | L8: 124/124 | M8: Submission 910296028 | N8: Yes
A9: 44991.954 | B9: 2023-03 | C9: 20 | D9: Valid Parentheses | E9: Easy | F9: Stack | G9: Wrong Answer | H9: C++ | I9: N/A | J9: N/A | L9: 5/92 | M9: Submission 910304068 | N9: Yes
A10: 44991.954 | B10: 2023-03 | C10: 20 | D10: Valid Parentheses | E10: Easy | F10: Stack | G10: Runtime Error | H10: C++ | I10: N/A | J10: N/A | L10: 6/92 | M10: Submission 910304549 | N10: Yes
A11: 44991.958 | B11: 2023-03 | C11: 20 | D11: Valid Parentheses | E11: Easy | F11: Stack | G11: Accepted | H11: C++ | I11: 5 ms | J11: 6.1 MB | K11: 0.9 | L11: 92/92 | M11: Submission 910307496 | N11: Yes
A12: 44991.99 | B12: 2023-03 | C12: 359 | D12: Logger Rate Limiter | E12: Easy | F12: Design | G12: Accepted | H12: C++ | I12: 92 ms | J12: 36.8 MB | K12: 5.2 | L12: 20/20 | M12: Submission 910337699 | N12: Yes
A13: 44991.996 | B13: 2023-03 | C13: 359 | D13: Logger Rate Limiter | E13: Easy | F13: Design | G13: Accepted | H13: C++ | I13: 70 ms | J13: 32.6 MB | K13: 5.2 | L13: 20/20 | M13: Submission 910342011 | N13: Yes
A14: 44992.004 | B14: 2023-03 | C14: 704 | D14: Binary Search | E14: Easy | F14: Binary Search | G14: Accepted | H14: C++ | I14: 47 ms | J14: 27.6 MB | K14: 0.1 | L14: 47/47 | M14: Submission 910349125 | N14: Yes
A15: 44992.022 | B15: 2023-03 | C15: 704 | D15: Binary Search | E15: Easy | F15: Binary Search | G15: Accepted | H15: C++ | I15: 43 ms | J15: 27.4 MB | K15: 0.1 | L15: 47/47 | M15: Submission 910363447 | N15: Yes
A16: 44992.026 | B16: 2023-03 | C16: 938 | D16: Range Sum of BST | E16: Easy | F16: Binary Search Tree | G16: Accepted | H16: C++ | I16: 135 ms | J16: 64.6 MB | K16: 3 | L16: 41/41 | M16: Submission 910366212 | N16: Yes
A17: 44992.026 | B17: 2023-03 | C17: 1 | D17: Two Sum | E17: Easy | F17: Arrays, Hashing & Sorting | G17: Accepted | H17: C++ | I17: 18 ms | J17: 11.2 MB | K17: 39.2 | L17: 57/57 | M17: Submission 910366686 | N17: Yes
A18: 44992.027 | B18: 2023-03 | C18: 13 | D18: Roman to Integer | E18: Easy | F18: Strings & Simulation | G18: Accepted | H18: C++ | I18: 11 ms | J18: 8.7 MB | K18: 26.4 | L18: 3999/3999 | M18: Submission 910366895 | N18: Yes
A19: 44992.027 | B19: 2023-03 | C19: 14 | D19: Longest Common Prefix | E19: Easy | F19: Strings & Simulation | G19: Accepted | H19: C++ | I19: 4 ms | J19: 9.2 MB | K19: 5.5 | L19: 124/124 | M19: Submission 910366984 | N19: Yes
A20: 44992.027 | B20: 2023-03 | C20: 20 | D20: Valid Parentheses | E20: Easy | F20: Stack | G20: Accepted | H20: C++ | I20: 4 ms | J20: 6.4 MB | K20: 1.3 | L20: 92/92 | M20: Submission 910367099 | N20: Yes
A21: 44992.027 | B21: 2023-03 | C21: 359 | D21: Logger Rate Limiter | E21: Easy | F21: Design | G21: Accepted | H21: C++ | I21: 76 ms | J21: 32.6 MB | K21: 5.2 | L21: 20/20 | M21: Submission 910367286 | N21: Yes
A22: 44992.035 | B22: 2023-03 | C22: 938 | D22: Range Sum of BST | E22: Easy | F22: Binary Search Tree | G22: Accepted | H22: C++ | I22: 152 ms | J22: 64.6 MB | K22: 3 | L22: 41/41 | M22: Submission 910373064 | N22: Yes
... A25: 44992.071 | B25: 2023-03 | C25: 56 | D25: Merge Intervals | E25: Medium | F25: Intervals & Sweep Line | G25: Accepted | H25: C++ | I25: 43 ms | J25: 20.1 MB | K25: 5.1 | L25: 170/170 | M25: Submission 910397138 | N25: Yes
A26: 44996.411 | B26: 2023-03 | C26: 70 | D26: Climbing Stairs | E26: Easy | F26: DP: 1D / Linear | G26: Wrong Answer | H26: C++ | I26: N/A | J26: N/A | L26: 43/45 | M26: Submission 913013853 | N26: Yes
A27: 44996.411 | B27: 2023-03 | C27: 70 | D27: Climbing Stairs | E27: Easy | F27: DP: 1D / Linear | G27: Accepted | H27: C++ | I27: 0 ms | J27: 6.4 MB | K27: 100 | L27: 45/45 | M27: Submission 913014080 | N27: Yes
A28: 44996.601 | B28: 2023-03 | C28: 1377 | D28: Frog Position After T Seconds | E28: Hard | F28: Graph: General BFS/DFS | G28: Accepted | H28: C++ | I28: 15 ms | J28: 15.4 MB | K28: 11 | L28: 204/204 | M28: Submission 913125591 | N28: Yes
A29: 44996.642 | B29: 2023-03 | C29: 1377 | D29: Frog Position After T Seconds | E29: Hard | F29: Graph: General BFS/DFS | G29: Accepted | H29: C++ | I29: 26 ms | J29: 15.2 MB | K29: 5.1 | L29: 204/204 | M29: Submission 913148665 | N29: Yes
A30: 44996.71 | B30: 2023-03 | C30: 213 | D30: House Robber II | E30: Medium | F30: DP: 1D / Linear | G30: Wrong Answer | H30: C++ | I30: N/A | J30: N/A | L30: 68/75 | M30: Submission 913184731 | N30: Yes
A31: 44996.711 | B31: 2023-03 | C31: 213 | D31: House Robber II | E31: Medium | F31: DP: 1D / Linear | G31: Wrong Answer | H31: C++ | I31: N/A | J31: N/A | L31: 73/75 | M31: Submission 913185027 | N31: Yes
A32: 44996.712 | B32: 2023-03 | C32: 213 | D32: House Robber II | E32: Medium | F32: DP: 1D / Linear | G32: Accepted | H32: C++ | I32: 3 ms | J32: 8 MB | K32: 6.5 | L32: 75/75 | M32: Submission 913185817 | N32: Yes
A33: 44997.468 | B33: 2023-03 | C33: 64 | D33: Minimum Path Sum | E33: Medium | F33: DP: Grid / 2D | G33: Wrong Answer | H33: C++ | I33: N/A | J33: N/A | L33: 39/61 | M33: Submission 913633670 | N33: Yes
A34: 44997.47 | B34: 2023-03 | C34: 64 | D34: Minimum Path Sum | E34: Medium | F34: DP: Grid / 2D | G34: Accepted | H34: C++ | I34: 15 ms | J34: 10.1 MB | K34: 5.9 | L34: 61/61 | M34: Submission 913635348 | N34: Yes
A35: 44997.496 | B35: 2023-03 | C35: 741 | D35: Cherry Pickup | E35: Hard | F35: DP: Grid / 2D | G35: Wrong Answer | H35: Java | I35: N/A | J35: N/A | L35: 49/59 | M35: Submission 913652420 | N35: Yes
A36: 44997.604 | B36: 2023-03 | C36: 741 | D36: Cherry Pickup | E36: Hard | F36: DP: Grid / 2D | G36: Wrong Answer | H36: C++ | I36: N/A | J36: N/A | L36: 48/59 | M36: Submission 913718323 | N36: Yes
A37: 44997.605 | B37: 2023-03 | C37: 741 | D37: Cherry Pickup | E37: Hard | F37: DP: Grid / 2D | G37: Accepted | H37: C++ | I37: 832 ms | J37: 587.2 MB | K37: 5.1 | L37: 59/59 | M37: Submission 913718543 | N37: Yes
A38: 44997.656 | B38: 2023-03 | C38: 1463 | D38: Cherry Pickup II | E38: Hard | F38: DP: Grid / 2D | G38: Accepted | H38: C++ | I38: 565 ms | J38: 445.7 MB | K38: 5 | L38: 59/59 | M38: Submission 913747384 | N38: Yes
A39: 44997.709 | B39: 2023-03 | C39: 1463 | D39: Cherry Pickup II | E39: Hard | F39: DP: Grid / 2D | G39: Accepted | H39: C++ | I39: 142 ms | J39: 17.4 MB | K39: 5 | L39: 59/59 | M39: Submission 913776663 | N39: Yes
A40: 44997.715 | B40: 2023-03 | C40: 62 | D40: Unique Paths | E40: Medium | F40: DP: Grid / 2D | G40: Accepted | H40: C++ | I40: 0 ms | J40: 6.6 MB | K40: 100 | L40: 63/63 | M40: Submission 913779888 | N40: Yes
A41: 44997.726 | B41: 2023-03 | C41: 63 | D41: Unique Paths II | E41: Medium | F41: DP: Grid / 2D | G41: Wrong Answer | H41: C++ | I41: N/A | J41: N/A | L41: 37/41 | M41: Submission 913786083 | N41: Yes
A42: 44997.728 | B42: 2023-03 | C42: 63 | D42: Unique Paths II | E42: Medium | F42: DP: Grid / 2D | G42: Accepted | H42: C++ | I42: 0 ms | J42: 8 MB | K42: 100 | L42: 41/41 | M42: Submission 913786813 | N42: Yes
A43: 44997.751 | B43: 2023-03 | C43: 120 | D43: Triangle | E43: Medium | F43: DP: Grid / 2D | G43: Accepted | H43: C++ | I43: 0 ms | J43: 19 MB | K43: 100 | L43: 44/44 | M43: Submission 913799505 | N43: Yes
A44: 44997.763 | B44: 2023-03 | C44: 931 | D44: Minimum Falling Path Sum | E44: Medium | F44: DP: Grid / 2D | G44: Accepted | H44: C++ | I44: 16 ms | J44: 10.3 MB | K44: 5.2 | L44: 49/49 | M44: Submission 913806269 | N44: Yes
A45: 44997.954 | B45: 2023-03 | C45: 416 | D45: Partition Equal Subset Sum | E45: Medium | F45: DP: Knapsack / Subset | G45: Accepted | H45: C++ | I45: 330 ms | J45: 178.1 MB | K45: 5 | L45: 141/141 | M45: Submission 913930133 | N45: Yes
A46: 44998.077 | B46: 2023-03 | C46: 322 | D46: Coin Change | E46: Medium | F46: DP: Knapsack / Subset | G46: Accepted | H46: C++ | I46: 110 ms | J46: 45.7 MB | K46: 5.6 | L46: 189/189 | M46: Submission 914009174 | N46: Yes
A47: 44998.078 | B47: 2023-03 | C47: 322 | D47: Coin Change | E47: Medium | F47: DP: Knapsack / Subset | G47: Wrong Answer | H47: C++ | I47: N/A | J47: N/A | L47: 51/189 | M47: Submission 914009772 | N47: Yes
A48: 44998.079 | B48: 2023-03 | C48: 322 | D48: Coin Change | E48: Medium | F48: DP: Knapsack / Subset | G48: Accepted | H48: C++ | I48: 100 ms | J48: 45.7 MB | K48: 5.7 | L48: 189/189 | M48: Submission 914009950 | N48: Yes
A49: 44998.098 | B49: 2023-03 | C49: 494 | D49: Target Sum | E49: Medium | F49: DP: Knapsack / Subset | G49: Accepted | H49: C++ | I49: 11 ms | J49: 12.3 MB | K49: 59.2 | L49: 140/140 | M49: Submission 914018995 | N49: Yes
A50: 44998.496 | B50: 2023-03 | C50: 1143 | D50: Longest Common Subsequence | E50: Medium | F50: DP: Strings (LCS, Edit, Matching) | G50: Time Limit Exceeded | H50: C++ | I50: N/A | J50: N/A | L50: 46/47 | M50: Submission 914209468 | N50: Yes
A51: 44998.496 | B51: 2023-03 | C51: 1143 | D51: Longest Common Subsequence | E51: Medium | F51: DP: Strings (LCS, Edit, Matching) | G51: Time Limit Exceeded | H51: C++ | I51: N/A | J51: N/A | L51: 42/47 | M51: Submission 914210046 | N51: Yes
A52: 44998.497 | B52: 2023-03 | C52: 1143 | D52: Longest Common Subsequence | E52: Medium | F52: DP: Strings (LCS, Edit, Matching) | G52: Accepted | H52: C++ | I52: 101 ms | J52: 24.7 MB | K52: 5.2 | L52: 47/47 | M52: Submission 914210738 | N52: Yes
A53: 44998.504 | B53: 2023-03 | C53: 1143 | D53: Longest Common Subsequence | E53: Medium | F53: DP: Strings (LCS, Edit, Matching) | G53: Accepted | H53: C++ | I53: 94 ms | J53: 42.4 MB | K53: 5.2 | L53: 47/47 | M53: Submission 914214722 | N53: Yes
A54: 44998.54 | B54: 2023-03 | C54: 1143 | D54: Longest Common Subsequence | E54: Medium | F54: DP: Strings (LCS, Edit, Matching) | G54: Accepted | H54: C++ | I54: 77 ms | J54: 43.3 MB | K54: 5.2 | L54: 47/47 | M54: Submission 914237588 | N54: Yes
A55: 44998.573 | B55: 2023-03 | C55: 516 | D55: Longest Palindromic Subsequence | E55: Medium | F55: DP: Strings (LCS, Edit, Matching) | G55: Accepted | H55: C++ | I55: 217 ms | J55: 72.9 MB | K55: 5 | L55: 86/86 | M55: Submission 914256431 | N55: Yes
A56: 44998.581 | B56: 2023-03 | C56: 1312 | D56: Minimum Insertion Steps to Make a String Palindrome | E56: Hard | F56: DP: Strings (LCS, Edit, Matching) | G56: Accepted | H56: C++ | I56: 113 ms | J56: 28.5 MB | K56: 5.3 | L56: 58/58 | M56: Submission 914260676 | N56: Yes
A57: 44998.61 | B57: 2023-03 | C57: 1092 | D57: Shortest Common Supersequence | E57: Hard | F57: DP: Strings (LCS, Edit, Matching) | G57: Wrong Answer | H57: C++ | I57: N/A | J57: N/A | L57: 9/47 | M57: Submission 914276409 | N57: Yes
A58: 44998.62 | B58: 2023-03 | C58: 1092 | D58: Shortest Common Supersequence | E58: Hard | F58: DP: Strings (LCS, Edit, Matching) | G58: Accepted | H58: C++ | I58: 36 ms | J58: 15.4 MB | K58: 6.3 | L58: 47/47 | M58: Submission 914282202 | N58: Yes
A59: 44998.665 | B59: 2023-03 | C59: 115 | D59: Distinct Subsequences | E59: Hard | F59: DP: Strings (LCS, Edit, Matching) | G59: Time Limit Exceeded | H59: C++ | I59: N/A | J59: N/A | L59: 50/65 | M59: Submission 914307571 | N59: Yes
A60: 44998.681 | B60: 2023-03 | C60: 115 | D60: Distinct Subsequences | E60: Hard | F60: DP: Strings (LCS, Edit, Matching) | G60: Runtime Error | H60: C++ | I60: N/A | J60: N/A | L60: 60/65 | M60: Submission 914316326 | N60: Yes
A61: 44998.688 | B61: 2023-03 | C61: 115 | D61: Distinct Subsequences | E61: Hard | F61: DP: Strings (LCS, Edit, Matching) | G61: Accepted | H61: C++ | I61: 48 ms | J61: 18.3 MB | K61: 7.4 | L61: 65/65 | M61: Submission 914319803 | N61: Yes
A62: 44998.701 | B62: 2023-03 | C62: 115 | D62: Distinct Subsequences | E62: Hard | F62: DP: Strings (LCS, Edit, Matching) | G62: Accepted | H62: C++ | I62: 30 ms | J62: 6.4 MB | K62: 50.1 | L62: 65/65 | M62: Submission 914326473 | N62: Yes
A63: 44998.71 | B63: 2023-03 | C63: 72 | D63: Edit Distance | E63: Medium | F63: DP: Strings (LCS, Edit, Matching) | G63: Accepted | H63: C++ | I63: 20 ms | J63: 9.1 MB | K63: 14.1 | L63: 1146/1146 | M63: Submission 914331669 | N63: Yes
A64: 44998.743 | B64: 2023-03 | C64: 44 | D64: Wildcard Matching | E64: Hard | F64: DP: Strings (LCS, Edit, Matching) | G64: Wrong Answer | H64: C++ | I64: N/A | J64: N/A | L64: 1479/1811 | M64: Submission 914349601 | N64: Yes
A65: 44998.746 | B65: 2023-03 | C65: 44 | D65: Wildcard Matching | E65: Hard | F65: DP: Strings (LCS, Edit, Matching) | G65: Time Limit Exceeded | H65: C++ | I65: N/A | J65: N/A | L65: 1611/1811 | M65: Submission 914351652 | N65: Yes
A66: 44998.75 | B66: 2023-03 | C66: 44 | D66: Wildcard Matching | E66: Hard | F66: DP: Strings (LCS, Edit, Matching) | G66: Accepted | H66: C++ | I66: 55 ms | J66: 28 MB | K66: 48.4 | L66: 1811/1811 | M66: Submission 914353737 | N66: Yes
A67: 44998.758 | B67: 2023-03 | C67: 121 | D67: Best Time to Buy and Sell Stock | E67: Easy | F67: DP: Buy & Sell Stock | G67: Accepted | H67: C++ | I67: 142 ms | J67: 97.3 MB | K67: 6.6 | L67: 211/211 | M67: Submission 914358315 | N67: Yes
A68: 44998.759 | B68: 2023-03 | C68: 121 | D68: Best Time to Buy and Sell Stock | E68: Easy | F68: DP: Buy & Sell Stock | G68: Accepted | H68: C++ | I68: 149 ms | J68: 93.3 MB | K68: 6.6 | L68: 211/211 | M68: Submission 914359211 | N68: Yes
A69: 44998.778 | B69: 2023-03 | C69: 122 | D69: Best Time to Buy and Sell Stock II | E69: Medium | F69: DP: Buy & Sell Stock | G69: Accepted | H69: C++ | I69: 18 ms | J69: 17.7 MB | K69: 5.1 | L69: 200/200 | M69: Submission 914371049 | N69: Yes
A70: 44998.778 | B70: 2023-03 | C70: 122 | D70: Best Time to Buy and Sell Stock II | E70: Medium | F70: DP: Buy & Sell Stock | G70: Accepted | H70: C++ | I70: 16 ms | J70: 17.7 MB | K70: 8.1 | L70: 200/200 | M70: Submission 914371469 | N70: Yes
A71: 44998.788 | B71: 2023-03 | C71: 122 | D71: Best Time to Buy and Sell Stock II | E71: Medium | F71: DP: Buy & Sell Stock | G71: Accepted | H71: C++ | I71: 11 ms | J71: 13.1 MB | K71: 26.7 | L71: 200/200 | M71: Submission 914377601 | N71: Yes
A72: 45000.613 | B72: 2023-03 | C72: 207 | D72: Course Schedule | E72: Medium | F72: Graph: Topological Sort | G72: Accepted | H72: C++ | I72: 24 ms | J72: 13.8 MB | K72: 6.7 | L72: 52/52 | M72: Submission 915544402 | N72: Yes
A73: 45001.42 | B73: 2023-03 | C73: 2187 | D73: Minimum Time to Complete Trips | E73: Medium | F73: Binary Search on Answer | G73: Wrong Answer | H73: C++ | I73: N/A | J73: N/A | L73: 86/124 | M73: Submission 916049625 | N73: Yes
A74: 45001.423 | B74: 2023-03 | C74: 2187 | D74: Minimum Time to Complete Trips | E74: Medium | F74: Binary Search on Answer | G74: Wrong Answer | H74: C++ | I74: N/A | J74: N/A | L74: 90/124 | M74: Submission 916051318 | N74: Yes
A75: 45001.424 | B75: 2023-03 | C75: 2187 | D75: Minimum Time to Complete Trips | E75: Medium | F75: Binary Search on Answer | G75: Wrong Answer | H75: C++ | I75: N/A | J75: N/A | L75: 90/124 | M75: Submission 916051943 | N75: Yes
A76: 45001.426 | B76: 2023-03 | C76: 2187 | D76: Minimum Time to Complete Trips | E76: Medium | F76: Binary Search on Answer | G76: Wrong Answer | H76: C++ | I76: N/A | J76: N/A | L76: 90/124 | M76: Submission 916053208 | N76: Yes
A77: 45001.427 | B77: 2023-03 | C77: 2187 | D77: Minimum Time to Complete Trips | E77: Medium | F77: Binary Search on Answer | G77: Wrong Answer | H77: C++ | I77: N/A | J77: N/A | L77: 120/124 | M77: Submission 916053597 | N77: Yes
A78: 45001.429 | B78: 2023-03 | C78: 2187 | D78: Minimum Time to Complete Trips | E78: Medium | F78: Binary Search on Answer | G78: Accepted | H78: C++ | I78: 416 ms | J78: 94.6 MB | K78: 5.2 | L78: 124/124 | M78: Submission 916054851 | N78: Yes
A79: 45001.429 | B79: 2023-03 | C79: 2187 | D79: Minimum Time to Complete Trips | E79: Medium | F79: Binary Search on Answer | G79: Wrong Answer | H79: C++ | I79: N/A | J79: N/A | L79: 120/124 | M79: Submission 916055160 | N79: Yes
A80: 45001.435 | B80: 2023-03 | C80: 2187 | D80: Minimum Time to Complete Trips | E80: Medium | F80: Binary Search on Answer | G80: Wrong Answer | H80: C++ | I80: N/A | J80: N/A | L80: 120/124 | M80: Submission 916058795 | N80: Yes
A81: 45001.566 | B81: 2023-03 | C81: 417 | D81: Pacific Atlantic Water Flow | E81: Medium | F81: Graph: Grid BFS/DFS | G81: Accepted | H81: C++ | I81: 43 ms | J81: 17.9 MB | K81: 9.1 | L81: 113/113 | M81: Submission 916138421 | N81: Yes
A82: 45001.739 | B82: 2023-03 | C82: 361 | D82: Bomb Enemy | E82: Medium | F82: DP: Grid / 2D | G82: Wrong Answer | H82: C++ | I82: N/A | J82: N/A | L82: 9/40 | M82: Submission 916248914 | N82: Yes
A83: 45001.741 | B83: 2023-03 | C83: 361 | D83: Bomb Enemy | E83: Medium | F83: DP: Grid / 2D | G83: Time Limit Exceeded | H83: C++ | I83: N/A | J83: N/A | L83: 39/40 | M83: Submission 916250425 | N83: Yes
A84: 45001.742 | B84: 2023-03 | C84: 361 | D84: Bomb Enemy | E84: Medium | F84: DP: Grid / 2D | G84: Time Limit Exceeded | H84: C++ | I84: N/A | J84: N/A | L84: 39/40 | M84: Submission 916250697 | N84: Yes
A85: 45001.769 | B85: 2023-03 | C85: 1428 | D85: Leftmost Column with at Least a One | E85: Medium | F85: Binary Search | G85: Accepted | H85: C++ | I85: 6 ms | J85: 8.1 MB | K85: 48.8 | L85: 37/37 | M85: Submission 916266861 | N85: Yes
A86: 45001.794 | B86: 2023-03 | C86: 1438 | D86: Longest Continuous Subarray With Absolute Diff Less Than or Equal to Limit | E86: Medium | F86: Sliding Window | G86: Wrong Answer | H86: C++ | I86: N/A | J86: N/A | L86: 60/61 | M86: Submission 916283389 | N86: Yes
A87: 45001.8 | B87: 2023-03 | C87: 1438 | D87: Longest Continuous Subarray With Absolute Diff Less Than or Equal to Limit | E87: Medium | F87: Sliding Window | G87: Wrong Answer | H87: C++ | I87: N/A | J87: N/A | L87: 60/61 | M87: Submission 916287128 | N87: Yes
A88: 45001.802 | B88: 2023-03 | C88: 1438 | D88: Longest Continuous Subarray With Absolute Diff Less Than or Equal to Limit | E88: Medium | F88: Sliding Window | G88: Accepted | H88: C++ | I88: 224 ms | J88: 78.7 MB | K88: 5.1 | L88: 61/61 | M88: Submission 916288522 | N88: Yes
A89: 45004.346 | B89: 2023-03 | C89: 715 | D89: Range Module | E89: Hard | F89: Segment Tree / BIT / Ordered Set | G89: Wrong Answer | H89: C++ | I89: N/A | J89: N/A | L89: 24/54 | M89: Submission 917810461 | N89: Yes
A90: 45004.353 | B90: 2023-03 | C90: 715 | D90: Range Module | E90: Hard | F90: Segment Tree / BIT / Ordered Set | G90: Accepted | H90: C++ | I90: 212 ms | J90: 71.8 MB | K90: 15.6 | L90: 54/54 | M90: Submission 917819658 | N90: Yes
A91: 45004.355 | B91: 2023-03 | C91: 715 | D91: Range Module | E91: Hard | F91: Segment Tree / BIT / Ordered Set | G91: Wrong Answer | H91: C++ | I91: N/A | J91: N/A | L91: 26/54 | M91: Submission 917821896 | N91: Yes
A92: 45004.355 | B92: 2023-03 | C92: 715 | D92: Range Module | E92: Hard | F92: Segment Tree / BIT / Ordered Set | G92: Accepted | H92: C++ | I92: 216 ms | J92: 71.6 MB | K92: 15.6 | L92: 54/54 | M92: Submission 917822373 | N92: Yes
A93: 45004.505 | B93: 2023-03 | C93: 200 | D93: Number of Islands | E93: Medium | F93: Graph: Grid BFS/DFS | G93: Accepted | H93: C++ | I93: 36 ms | J93: 12.1 MB | K93: 12.2 | L93: 49/49 | M93: Submission 917948684 | N93: Yes
A94: 45005.695 | B94: 2023-03 | C94: 32 | D94: Longest Valid Parentheses | E94: Hard | F94: Stack | G94: Accepted | H94: C++ | I94: 0 ms | J94: 7.4 MB | K94: 100 | L94: 231/231 | M94: Submission 918711517 | N94: Yes
A95: 45005.703 | B95: 2023-03 | C95: 32 | D95: Longest Valid Parentheses | E95: Hard | F95: Stack | G95: Accepted | H95: C++ | I95: 0 ms | J95: 6.9 MB | K95: 100 | L95: 231/231 | M95: Submission 918716653 | N95: Yes
A96: 45005.708 | B96: 2023-03 | C96: 25 | D96: Reverse Nodes in k-Group | E96: Hard | F96: Linked List | G96: Accepted | H96: C++ | I96: 3 ms | J96: 11.4 MB | K96: 2.3 | L96: 62/62 | M96: Submission 918719901 | N96: Yes
A97: 45005.736 | B97: 2023-03 | C97: 146 | D97: LRU Cache | E97: Medium | F97: Design | G97: Wrong Answer | H97: C++ | I97: N/A | J97: N/A | L97: 12/22 | M97: Submission 918738327 | N97: Yes
A98: 45005.737 | B98: 2023-03 | C98: 146 | D98: LRU Cache | E98: Medium | F98: Design | G98: Accepted | H98: C++ | I98: 593 ms | J98: 186 MB | K98: 5 | L98: 22/22 | M98: Submission 918739058 | N98: Yes
A99: 45005.772 | B99: 2023-03 | C99: 5 | D99: Longest Palindromic Substring | E99: Medium | F99: Two Pointers | G99: Wrong Answer | H99: C++ | I99: N/A | J99: N/A | L99: 71/141 | M99: Submission 918763865 | N99: Yes
A100: 45005.773 | B100: 2023-03 | C100: 5 | D100: Longest Palindromic Substring | E100: Medium | F100: Two Pointers | G100: Accepted | H100: C++ | I100: 196 ms | J100: 35 MB | K100: 18.4 | L100: 141/141 | M100: Submission 918764471 | N100: Yes
A101: 45005.774 | B101: 2023-03 | C101: 5 | D101: Longest Palindromic Substring | E101: Medium | F101: Two Pointers | G101: Accepted | H101: C++ | I101: 355 ms | J101: 34.9 MB | K101: 12.6 | L101: 141/141 | M101: Submission 918765526 | N101: Yes
A102: 45005.775 | B102: 2023-03 | C102: 5 | D102: Longest Palindromic Substring | E102: Medium | F102: Two Pointers | G102: Accepted | H102: C++ | I102: 211 ms | J102: 35 MB | K102: 17.6 | L102: 141/141 | M102: Submission 918765732 | N102: Yes
...

Sheet Pattern Summary
A1: Topic group | B1: Pattern | C1: Easy | D1: Medium | E1: Hard | F1: Total (your list) | G1: Other problems | H1: First-try AC rate (list) | I1: Avg submissions per problem (list) | J1: Failed attempts before AC (list)
A2: Arrays & Strings | B2: Arrays, Hashing & Sorting | C2: =COUNTIFS('Solved Problems'!$E$2:$E$278,$B2,'Solved Problems'!$D$2:$D$278,"Easy") | D2: =COUNTIFS('Solved Problems'!$E$2:$E$278,$B2,'Solved Problems'!$D$2:$D$278,"Medium") | E2: =COUNTIFS('Solved Problems'!$E$2:$E$278,$B2,'Solved Problems'!$D$2:$D$278,"Hard") | F2: =SUM(C2:E2) | G2: =COUNTIFS('Other Problems'!$E$2:$E$119,$B2) | H2: =IF(F2=0,"",COUNTIFS('Solved Problems'!$E$2:$E$278,$B2,'Solved Problems'!$P$2:$P$278,"Yes")/F2) | I2: =IF(F2=0,"",SUMIFS('Solved Problems'!$M$2:$M$278,'Solved Problems'!$E$2:$E$278,$B2)/F2) | J2: =SUMIFS('Solved Problems'!$O$2:$O$278,'Solved Problems'!$E$2:$E$278,$B2)
A3: Arrays & Strings | B3: Two Pointers | C3: =COUNTIFS('Solved Problems'!$E$2:$E$278,$B3,'Solved Problems'!$D$2:$D$278,"Easy") | D3: =COUNTIFS('Solved Problems'!$E$2:$E$278,$B3,'Solved Problems'!$D$2:$D$278,"Medium") | E3: =COUNTIFS('Solved Problems'!$E$2:$E$278,$B3,'Solved Problems'!$D$2:$D$278,"Hard") | F3: =SUM(C3:E3) | G3: =COUNTIFS('Other Problems'!$E$2:$E$119,$B3) | H3: =IF(F3=0,"",COUNTIFS('Solved Problems'!$E$2:$E$278,$B3,'Solved Problems'!$P$2:$P$278,"Yes")/F3) | I3: =IF(F3=0,"",SUMIFS('Solved Problems'!$M$2:$M$278,'Solved Problems'!$E$2:$E$278,$B3)/F3) | J3: =SUMIFS('Solved Problems'!$O$2:$O$278,'Solved Problems'!$E$2:$E$278,$B3)
A4: Arrays & Strings | B4: Sliding Window | C4: =COUNTIFS('Solved Problems'!$E$2:$E$278,$B4,'Solved Problems'!$D$2:$D$278,"Easy") | D4: =COUNTIFS('Solved Problems'!$E$2:$E$278,$B4,'Solved Problems'!$D$2:$D$278,"Medium") | E4: =COUNTIFS('Solved Problems'!$E$2:$E$278,$B4,'Solved Problems'!$D$2:$D$278,"Hard") | F4: =SUM(C4:E4) | G4: =COUNTIFS('Other Problems'!$E$2:$E$119,$B4) | H4: =IF(F4=0,"",COUNTIFS('Solved Problems'!$E$2:$E$278,$B4,'Solved Problems'!$P$2:$P$278,"Yes")/F4) | I4: =IF(F4=0,"",SUMIFS('Solved Problems'!$M$2:$M$278,'Solved Problems'!$E$2:$E$278,$B4)/F4) | J4: =SUMIFS('Solved Problems'!$O$2:$O$278,'Solved Problems'!$E$2:$E$278,$B4)
A5: Arrays & Strings | B5: Prefix Sum & Difference Array | C5: =COUNTIFS('Solved Problems'!$E$2:$E$278,$B5,'Solved Problems'!$D$2:$D$278,"Easy") | D5: =COUNTIFS('Solved Problems'!$E$2:$E$278,$B5,'Solved Problems'!$D$2:$D$278,"Medium") | E5: =COUNTIFS('Solved Problems'!$E$2:$E$278,$B5,'Solved Problems'!$D$2:$D$278,"Hard") | F5: =SUM(C5:E5) | G5: =COUNTIFS('Other Problems'!$E$2:$E$119,$B5) | H5: =IF(F5=0,"",COUNTIFS('Solved Problems'!$E$2:$E$278,$B5,'Solved Problems'!$P$2:$P$278,"Yes")/F5) | I5: =IF(F5=0,"",SUMIFS('Solved Problems'!$M$2:$M$278,'Solved Problems'!$E$2:$E$278,$B5)/F5) | J5: =SUMIFS('Solved Problems'!$O$2:$O$278,'Solved Problems'!$E$2:$E$278,$B5)
A6: Arrays & Strings | B6: Math & Bit Manipulation | C6: =COUNTIFS('Solved Problems'!$E$2:$E$278,$B6,'Solved Problems'!$D$2:$D$278,"Easy") | D6: =COUNTIFS('Solved Problems'!$E$2:$E$278,$B6,'Solved Problems'!$D$2:$D$278,"Medium") | E6: =COUNTIFS('Solved Problems'!$E$2:$E$278,$B6,'Solved Problems'!$D$2:$D$278,"Hard") | F6: =SUM(C6:E6) | G6: =COUNTIFS('Other Problems'!$E$2:$E$119,$B6) | H6: =IF(F6=0,"",COUNTIFS('Solved Problems'!$E$2:$E$278,$B6,'Solved Problems'!$P$2:$P$278,"Yes")/F6) | I6: =IF(F6=0,"",SUMIFS('Solved Problems'!$M$2:$M$278,'Solved Problems'!$E$2:$E$278,$B6)/F6) | J6: =SUMIFS('Solved Problems'!$O$2:$O$278,'Solved Problems'!$E$2:$E$278,$B6)
A7: Arrays & Strings | B7: Strings & Simulation | C7: =COUNTIFS('Solved Problems'!$E$2:$E$278,$B7,'Solved Problems'!$D$2:$D$278,"Easy") | D7: =COUNTIFS('Solved Problems'!$E$2:$E$278,$B7,'Solved Problems'!$D$2:$D$278,"Medium") | E7: =COUNTIFS('Solved Problems'!$E$2:$E$278,$B7,'Solved Problems'!$D$2:$D$278,"Hard") | F7: =SUM(C7:E7) | G7: =COUNTIFS('Other Problems'!$E$2:$E$119,$B7) | H7: =IF(F7=0,"",COUNTIFS('Solved Problems'!$E$2:$E$278,$B7,'Solved Problems'!$P$2:$P$278,"Yes")/F7) | I7: =IF(F7=0,"",SUMIFS('Solved Problems'!$M$2:$M$278,'Solved Problems'!$E$2:$E$278,$B7)/F7) | J7: =SUMIFS('Solved Problems'!$O$2:$O$278,'Solved Problems'!$E$2:$E$278,$B7)
A8: Searching | B8: Binary Search | C8: =COUNTIFS('Solved Problems'!$E$2:$E$278,$B8,'Solved Problems'!$D$2:$D$278,"Easy") | D8: =COUNTIFS('Solved Problems'!$E$2:$E$278,$B8,'Solved Problems'!$D$2:$D$278,"Medium") | E8: =COUNTIFS('Solved Problems'!$E$2:$E$278,$B8,'Solved Problems'!$D$2:$D$278,"Hard") | F8: =SUM(C8:E8) | G8: =COUNTIFS('Other Problems'!$E$2:$E$119,$B8) | H8: =IF(F8=0,"",COUNTIFS('Solved Problems'!$E$2:$E$278,$B8,'Solved Problems'!$P$2:$P$278,"Yes")/F8) | I8: =IF(F8=0,"",SUMIFS('Solved Problems'!$M$2:$M$278,'Solved Problems'!$E$2:$E$278,$B8)/F8) | J8: =SUMIFS('Solved Problems'!$O$2:$O$278,'Solved Problems'!$E$2:$E$278,$B8)
A9: Searching | B9: Binary Search on Answer | C9: =COUNTIFS('Solved Problems'!$E$2:$E$278,$B9,'Solved Problems'!$D$2:$D$278,"Easy") | D9: =COUNTIFS('Solved Problems'!$E$2:$E$278,$B9,'Solved Problems'!$D$2:$D$278,"Medium") | E9: =COUNTIFS('Solved Problems'!$E$2:$E$278,$B9,'Solved Problems'!$D$2:$D$278,"Hard") | F9: =SUM(C9:E9) | G9: =COUNTIFS('Other Problems'!$E$2:$E$119,$B9) | H9: =IF(F9=0,"",COUNTIFS('Solved Problems'!$E$2:$E$278,$B9,'Solved Problems'!$P$2:$P$278,"Yes")/F9) | I9: =IF(F9=0,"",SUMIFS('Solved Problems'!$M$2:$M$278,'Solved Problems'!$E$2:$E$278,$B9)/F9) | J9: =SUMIFS('Solved Problems'!$O$2:$O$278,'Solved Problems'!$E$2:$E$278,$B9)
A10: Stacks & Queues | B10: Stack | C10: =COUNTIFS('Solved Problems'!$E$2:$E$278,$B10,'Solved Problems'!$D$2:$D$278,"Easy") | D10: =COUNTIFS('Solved Problems'!$E$2:$E$278,$B10,'Solved Problems'!$D$2:$D$278,"Medium") | E10: =COUNTIFS('Solved Problems'!$E$2:$E$278,$B10,'Solved Problems'!$D$2:$D$278,"Hard") | F10: =SUM(C10:E10) | G10: =COUNTIFS('Other Problems'!$E$2:$E$119,$B10) | H10: =IF(F10=0,"",COUNTIFS('Solved Problems'!$E$2:$E$278,$B10,'Solved Problems'!$P$2:$P$278,"Yes")/F10) | I10: =IF(F10=0,"",SUMIFS('Solved Problems'!$M$2:$M$278,'Solved Problems'!$E$2:$E$278,$B10)/F10) | J10: =SUMIFS('Solved Problems'!$O$2:$O$278,'Solved Problems'!$E$2:$E$278,$B10)
A11: Stacks & Queues | B11: Monotonic Stack / Deque | C11: =COUNTIFS('Solved Problems'!$E$2:$E$278,$B11,'Solved Problems'!$D$2:$D$278,"Easy") | D11: =COUNTIFS('Solved Problems'!$E$2:$E$278,$B11,'Solved Problems'!$D$2:$D$278,"Medium") | E11: =COUNTIFS('Solved Problems'!$E$2:$E$278,$B11,'Solved Problems'!$D$2:$D$278,"Hard") | F11: =SUM(C11:E11) | G11: =COUNTIFS('Other Problems'!$E$2:$E$119,$B11) | H11: =IF(F11=0,"",COUNTIFS('Solved Problems'!$E$2:$E$278,$B11,'Solved Problems'!$P$2:$P$278,"Yes")/F11) | I11: =IF(F11=0,"",SUMIFS('Solved Problems'!$M$2:$M$278,'Solved Problems'!$E$2:$E$278,$B11)/F11) | J11: =SUMIFS('Solved Problems'!$O$2:$O$278,'Solved Problems'!$E$2:$E$278,$B11)
A12: Linked List | B12: Linked List | C12: =COUNTIFS('Solved Problems'!$E$2:$E$278,$B12,'Solved Problems'!$D$2:$D$278,"Easy") | D12: =COUNTIFS('Solved Problems'!$E$2:$E$278,$B12,'Solved Problems'!$D$2:$D$278,"Medium") | E12: =COUNTIFS('Solved Problems'!$E$2:$E$278,$B12,'Solved Problems'!$D$2:$D$278,"Hard") | F12: =SUM(C12:E12) | G12: =COUNTIFS('Other Problems'!$E$2:$E$119,$B12) | H12: =IF(F12=0,"",COUNTIFS('Solved Problems'!$E$2:$E$278,$B12,'Solved Problems'!$P$2:$P$278,"Yes")/F12) | I12: =IF(F12=0,"",SUMIFS('Solved Problems'!$M$2:$M$278,'Solved Problems'!$E$2:$E$278,$B12)/F12) | J12: =SUMIFS('Solved Problems'!$O$2:$O$278,'Solved Problems'!$E$2:$E$278,$B12)
A13: Trees | B13: Binary Tree (DFS & Recursion) | C13: =COUNTIFS('Solved Problems'!$E$2:$E$278,$B13,'Solved Problems'!$D$2:$D$278,"Easy") | D13: =COUNTIFS('Solved Problems'!$E$2:$E$278,$B13,'Solved Problems'!$D$2:$D$278,"Medium") | E13: =COUNTIFS('Solved Problems'!$E$2:$E$278,$B13,'Solved Problems'!$D$2:$D$278,"Hard") | F13: =SUM(C13:E13) | G13: =COUNTIFS('Other Problems'!$E$2:$E$119,$B13) | H13: =IF(F13=0,"",COUNTIFS('Solved Problems'!$E$2:$E$278,$B13,'Solved Problems'!$P$2:$P$278,"Yes")/F13) | I13: =IF(F13=0,"",SUMIFS('Solved Problems'!$M$2:$M$278,'Solved Problems'!$E$2:$E$278,$B13)/F13) | J13: =SUMIFS('Solved Problems'!$O$2:$O$278,'Solved Problems'!$E$2:$E$278,$B13)
... A36: Advanced Data Structures | B36: Segment Tree / BIT / Ordered Set | C36: =COUNTIFS('Solved Problems'!$E$2:$E$278,$B36,'Solved Problems'!$D$2:$D$278,"Easy") | D36: =COUNTIFS('Solved Problems'!$E$2:$E$278,$B36,'Solved Problems'!$D$2:$D$278,"Medium") | E36: =COUNTIFS('Solved Problems'!$E$2:$E$278,$B36,'Solved Problems'!$D$2:$D$278,"Hard") | F36: =SUM(C36:E36) | G36: =COUNTIFS('Other Problems'!$E$2:$E$119,$B36) | H36: =IF(F36=0,"",COUNTIFS('Solved Problems'!$E$2:$E$278,$B36,'Solved Problems'!$P$2:$P$278,"Yes")/F36) | I36: =IF(F36=0,"",SUMIFS('Solved Problems'!$M$2:$M$278,'Solved Problems'!$E$2:$E$278,$B36)/F36) | J36: =SUMIFS('Solved Problems'!$O$2:$O$278,'Solved Problems'!$E$2:$E$278,$B36)
B37: Total | C37: =SUM(C2:C36) | D37: =SUM(D2:D36) | E37: =SUM(E2:E36) | F37: =SUM(F2:F36) | G37: =SUM(G2:G36) | J37: =SUM(J2:J36)

Sheet Timeline
A1: Month | B1: Submissions | C1: Accepted | D1: Acceptance rate | E1: New problems solved (list) | F1: New problems solved (other) | G1: C++ subs | H1: Python subs | I1: Java subs
A2: 2023-03 | B2: =COUNTIFS(Submissions!$B$2:$B$1621,$A2) | C2: =COUNTIFS(Submissions!$B$2:$B$1621,$A2,Submissions!$G$2:$G$1621,"Accepted") | D2: =IF(B2=0,"",C2/B2) | E2: =COUNTIFS('Solved Problems'!$Y$2:$Y$278,$A2) | F2: =COUNTIFS('Other Problems'!$Y$2:$Y$119,$A2) | G2: =COUNTIFS(Submissions!$B$2:$B$1621,$A2,Submissions!$H$2:$H$1621,"C++") | H2: =COUNTIFS(Submissions!$B$2:$B$1621,$A2,Submissions!$H$2:$H$1621,"Python3")+COUNTIFS(Submissions!$B$2:$B$1621,$A2,Submissions!$H$2:$H$1621,"Python") | I2: =COUNTIFS(Submissions!$B$2:$B$1621,$A2,Submissions!$H$2:$H$1621,"Java")
A3: 2023-04 | B3: =COUNTIFS(Submissions!$B$2:$B$1621,$A3) | C3: =COUNTIFS(Submissions!$B$2:$B$1621,$A3,Submissions!$G$2:$G$1621,"Accepted") | D3: =IF(B3=0,"",C3/B3) | E3: =COUNTIFS('Solved Problems'!$Y$2:$Y$278,$A3) | F3: =COUNTIFS('Other Problems'!$Y$2:$Y$119,$A3) | G3: =COUNTIFS(Submissions!$B$2:$B$1621,$A3,Submissions!$H$2:$H$1621,"C++") | H3: =COUNTIFS(Submissions!$B$2:$B$1621,$A3,Submissions!$H$2:$H$1621,"Python3")+COUNTIFS(Submissions!$B$2:$B$1621,$A3,Submissions!$H$2:$H$1621,"Python") | I3: =COUNTIFS(Submissions!$B$2:$B$1621,$A3,Submissions!$H$2:$H$1621,"Java")
A4: 2023-05 | B4: =COUNTIFS(Submissions!$B$2:$B$1621,$A4) | C4: =COUNTIFS(Submissions!$B$2:$B$1621,$A4,Submissions!$G$2:$G$1621,"Accepted") | D4: =IF(B4=0,"",C4/B4) | E4: =COUNTIFS('Solved Problems'!$Y$2:$Y$278,$A4) | F4: =COUNTIFS('Other Problems'!$Y$2:$Y$119,$A4) | G4: =COUNTIFS(Submissions!$B$2:$B$1621,$A4,Submissions!$H$2:$H$1621,"C++") | H4: =COUNTIFS(Submissions!$B$2:$B$1621,$A4,Submissions!$H$2:$H$1621,"Python3")+COUNTIFS(Submissions!$B$2:$B$1621,$A4,Submissions!$H$2:$H$1621,"Python") | I4: =COUNTIFS(Submissions!$B$2:$B$1621,$A4,Submissions!$H$2:$H$1621,"Java")
A5: 2023-06 | B5: =COUNTIFS(Submissions!$B$2:$B$1621,$A5) | C5: =COUNTIFS(Submissions!$B$2:$B$1621,$A5,Submissions!$G$2:$G$1621,"Accepted") | D5: =IF(B5=0,"",C5/B5) | E5: =COUNTIFS('Solved Problems'!$Y$2:$Y$278,$A5) | F5: =COUNTIFS('Other Problems'!$Y$2:$Y$119,$A5) | G5: =COUNTIFS(Submissions!$B$2:$B$1621,$A5,Submissions!$H$2:$H$1621,"C++") | H5: =COUNTIFS(Submissions!$B$2:$B$1621,$A5,Submissions!$H$2:$H$1621,"Python3")+COUNTIFS(Submissions!$B$2:$B$1621,$A5,Submissions!$H$2:$H$1621,"Python") | I5: =COUNTIFS(Submissions!$B$2:$B$1621,$A5,Submissions!$H$2:$H$1621,"Java")
A6: 2023-07 | B6: =COUNTIFS(Submissions!$B$2:$B$1621,$A6) | C6: =COUNTIFS(Submissions!$B$2:$B$1621,$A6,Submissions!$G$2:$G$1621,"Accepted") | D6: =IF(B6=0,"",C6/B6) | E6: =COUNTIFS('Solved Problems'!$Y$2:$Y$278,$A6) | F6: =COUNTIFS('Other Problems'!$Y$2:$Y$119,$A6) | G6: =COUNTIFS(Submissions!$B$2:$B$1621,$A6,Submissions!$H$2:$H$1621,"C++") | H6: =COUNTIFS(Submissions!$B$2:$B$1621,$A6,Submissions!$H$2:$H$1621,"Python3")+COUNTIFS(Submissions!$B$2:$B$1621,$A6,Submissions!$H$2:$H$1621,"Python") | I6: =COUNTIFS(Submissions!$B$2:$B$1621,$A6,Submissions!$H$2:$H$1621,"Java")
A7: 2023-08 | B7: =COUNTIFS(Submissions!$B$2:$B$1621,$A7) | C7: =COUNTIFS(Submissions!$B$2:$B$1621,$A7,Submissions!$G$2:$G$1621,"Accepted") | D7: =IF(B7=0,"",C7/B7) | E7: =COUNTIFS('Solved Problems'!$Y$2:$Y$278,$A7) | F7: =COUNTIFS('Other Problems'!$Y$2:$Y$119,$A7) | G7: =COUNTIFS(Submissions!$B$2:$B$1621,$A7,Submissions!$H$2:$H$1621,"C++") | H7: =COUNTIFS(Submissions!$B$2:$B$1621,$A7,Submissions!$H$2:$H$1621,"Python3")+COUNTIFS(Submissions!$B$2:$B$1621,$A7,Submissions!$H$2:$H$1621,"Python") | I7: =COUNTIFS(Submissions!$B$2:$B$1621,$A7,Submissions!$H$2:$H$1621,"Java")
A8: 2023-09 | B8: =COUNTIFS(Submissions!$B$2:$B$1621,$A8) | C8: =COUNTIFS(Submissions!$B$2:$B$1621,$A8,Submissions!$G$2:$G$1621,"Accepted") | D8: =IF(B8=0,"",C8/B8) | E8: =COUNTIFS('Solved Problems'!$Y$2:$Y$278,$A8) | F8: =COUNTIFS('Other Problems'!$Y$2:$Y$119,$A8) | G8: =COUNTIFS(Submissions!$B$2:$B$1621,$A8,Submissions!$H$2:$H$1621,"C++") | H8: =COUNTIFS(Submissions!$B$2:$B$1621,$A8,Submissions!$H$2:$H$1621,"Python3")+COUNTIFS(Submissions!$B$2:$B$1621,$A8,Submissions!$H$2:$H$1621,"Python") | I8: =COUNTIFS(Submissions!$B$2:$B$1621,$A8,Submissions!$H$2:$H$1621,"Java")
A9: 2023-10 | B9: =COUNTIFS(Submissions!$B$2:$B$1621,$A9) | C9: =COUNTIFS(Submissions!$B$2:$B$1621,$A9,Submissions!$G$2:$G$1621,"Accepted") | D9: =IF(B9=0,"",C9/B9) | E9: =COUNTIFS('Solved Problems'!$Y$2:$Y$278,$A9) | F9: =COUNTIFS('Other Problems'!$Y$2:$Y$119,$A9) | G9: =COUNTIFS(Submissions!$B$2:$B$1621,$A9,Submissions!$H$2:$H$1621,"C++") | H9: =COUNTIFS(Submissions!$B$2:$B$1621,$A9,Submissions!$H$2:$H$1621,"Python3")+COUNTIFS(Submissions!$B$2:$B$1621,$A9,Submissions!$H$2:$H$1621,"Python") | I9: =COUNTIFS(Submissions!$B$2:$B$1621,$A9,Submissions!$H$2:$H$1621,"Java")
A10: 2023-11 | B10: =COUNTIFS(Submissions!$B$2:$B$1621,$A10) | C10: =COUNTIFS(Submissions!$B$2:$B$1621,$A10,Submissions!$G$2:$G$1621,"Accepted") | D10: =IF(B10=0,"",C10/B10) | E10: =COUNTIFS('Solved Problems'!$Y$2:$Y$278,$A10) | F10: =COUNTIFS('Other Problems'!$Y$2:$Y$119,$A10) | G10: =COUNTIFS(Submissions!$B$2:$B$1621,$A10,Submissions!$H$2:$H$1621,"C++") | H10: =COUNTIFS(Submissions!$B$2:$B$1621,$A10,Submissions!$H$2:$H$1621,"Python3")+COUNTIFS(Submissions!$B$2:$B$1621,$A10,Submissions!$H$2:$H$1621,"Python") | I10: =COUNTIFS(Submissions!$B$2:$B$1621,$A10,Submissions!$H$2:$H$1621,"Java")
A11: 2023-12 | B11: =COUNTIFS(Submissions!$B$2:$B$1621,$A11) | C11: =COUNTIFS(Submissions!$B$2:$B$1621,$A11,Submissions!$G$2:$G$1621,"Accepted") | D11: =IF(B11=0,"",C11/B11) | E11: =COUNTIFS('Solved Problems'!$Y$2:$Y$278,$A11) | F11: =COUNTIFS('Other Problems'!$Y$2:$Y$119,$A11) | G11: =COUNTIFS(Submissions!$B$2:$B$1621,$A11,Submissions!$H$2:$H$1621,"C++") | H11: =COUNTIFS(Submissions!$B$2:$B$1621,$A11,Submissions!$H$2:$H$1621,"Python3")+COUNTIFS(Submissions!$B$2:$B$1621,$A11,Submissions!$H$2:$H$1621,"Python") | I11: =COUNTIFS(Submissions!$B$2:$B$1621,$A11,Submissions!$H$2:$H$1621,"Java")
A12: 2024-01 | B12: =COUNTIFS(Submissions!$B$2:$B$1621,$A12) | C12: =COUNTIFS(Submissions!$B$2:$B$1621,$A12,Submissions!$G$2:$G$1621,"Accepted") | D12: =IF(B12=0,"",C12/B12) | E12: =COUNTIFS('Solved Problems'!$Y$2:$Y$278,$A12) | F12: =COUNTIFS('Other Problems'!$Y$2:$Y$119,$A12) | G12: =COUNTIFS(Submissions!$B$2:$B$1621,$A12,Submissions!$H$2:$H$1621,"C++") | H12: =COUNTIFS(Submissions!$B$2:$B$1621,$A12,Submissions!$H$2:$H$1621,"Python3")+COUNTIFS(Submissions!$B$2:$B$1621,$A12,Submissions!$H$2:$H$1621,"Python") | I12: =COUNTIFS(Submissions!$B$2:$B$1621,$A12,Submissions!$H$2:$H$1621,"Java")
A13: 2024-02 | B13: =COUNTIFS(Submissions!$B$2:$B$1621,$A13) | C13: =COUNTIFS(Submissions!$B$2:$B$1621,$A13,Submissions!$G$2:$G$1621,"Accepted") | D13: =IF(B13=0,"",C13/B13) | E13: =COUNTIFS('Solved Problems'!$Y$2:$Y$278,$A13) | F13: =COUNTIFS('Other Problems'!$Y$2:$Y$119,$A13) | G13: =COUNTIFS(Submissions!$B$2:$B$1621,$A13,Submissions!$H$2:$H$1621,"C++") | H13: =COUNTIFS(Submissions!$B$2:$B$1621,$A13,Submissions!$H$2:$H$1621,"Python3")+COUNTIFS(Submissions!$B$2:$B$1621,$A13,Submissions!$H$2:$H$1621,"Python") | I13: =COUNTIFS(Submissions!$B$2:$B$1621,$A13,Submissions!$H$2:$H$1621,"Java")
... A45: 2026-10 | B45: =COUNTIFS(Submissions!$B$2:$B$1621,$A45) | C45: =COUNTIFS(Submissions!$B$2:$B$1621,$A45,Submissions!$G$2:$G$1621,"Accepted") | D45: =IF(B45=0,"",C45/B45) | E45: =COUNTIFS('Solved Problems'!$Y$2:$Y$278,$A45) | F45: =COUNTIFS('Other Problems'!$Y$2:$Y$119,$A45) | G45: =COUNTIFS(Submissions!$B$2:$B$1621,$A45,Submissions!$H$2:$H$1621,"C++") | H45: =COUNTIFS(Submissions!$B$2:$B$1621,$A45,Submissions!$H$2:$H$1621,"Python3")+COUNTIFS(Submissions!$B$2:$B$1621,$A45,Submissions!$H$2:$H$1621,"Python") | I45: =COUNTIFS(Submissions!$B$2:$B$1621,$A45,Submissions!$H$2:$H$1621,"Java")
